Off_Chip_Protocols/SPI_Protocol/SPI_in_Mode_0/3_SPI_Slave.v
module spi_slave(
  input i_clk,     //system clock of slave
  input sclk,       //synchronous clock from master
  input cs,          //slave select
  input i_mosi,
  input [7:0] i_tx_data,    //data which is to be send to master
  
  output reg o_miso,
  output reg [7:0] o_rx_data,   //data received from master
  output reg s_done,
  output reg s_busy

);
  
  reg [7:0] tx_shift;
  reg [7:0] rx_shift;
  
  reg sclk_p;
  reg [3:0] bit_count;
  
  reg [1:0] state,next;
  localparam IDLE=2'b00,
             LOAD=2'b01,
             TRANSFER=2'b10,
             DONE=2'b11;

 // ╔══════════════════════════════════════╗
 // ║  STATE TRANSITION SEQUENTIAL LOGIC   ║
 // ╚══════════════════════════════════════╝
  
  always@(posedge i_clk)begin
	if(cs)            //CS acts as reset for slave as it doesnt have reset for its own
      state<=IDLE;
    else
      state<=next;
  end
  
  
 // ╔══════════════════════════════════════╗
 // ║    NEXT STATE COMBINATIONAL LOGIC    ║
 // ╚══════════════════════════════════════╝
  always @(*)begin
    next=state;
    case(state)
           IDLE:next=(cs==0)?LOAD:IDLE;
           LOAD:next=TRANSFER;
           TRANSFER:next=(bit_count==4'd8)?DONE:TRANSFER;
           DONE:next=(!cs)?DONE:IDLE;
           default:next=IDLE;
    endcase
  end

 // ╔══════════════════════════════════════╗
 // ║         OUTPUTS UPON STATES          ║
 // ╚══════════════════════════════════════╝	
       always@(posedge i_clk)begin
         if(cs)begin
          bit_count<=0;
          tx_shift<=0;
          rx_shift<=0;
          sclk_p<=0;
          o_miso<=1'bz;
          s_busy<=0;
          s_done<=0;
          o_rx_data<=0;
        end
        else begin
          sclk_p<=sclk;
          s_done <= 0; 
          
          case(state)
              IDLE:begin
                bit_count<=0;
                s_busy<=0;
                o_miso<=1'bz;
              end
              LOAD:begin               
                tx_shift<=i_tx_data;  //loading the input data(to be sent) on a shift register
                rx_shift<=0;
                o_miso<=i_tx_data[7]; //preloading of MSB before the sampling edge
                s_busy<=1;       // the master became busy
                bit_count<=0;   //making the count 0
              end
              TRANSFER:begin
                
                if (sclk==1 && sclk_p==0)begin //rising edge
                  rx_shift<={rx_shift[6:0],i_mosi};  //input from slave is sampled here
                 end
                
                
                if(sclk==0 && sclk_p==1)begin  //falling edge
                  if(bit_count<=7)begin
                    tx_shift<={tx_shift[6:0],1'b0};  //output to slave is changed here
                    o_miso<=tx_shift[6];
                    bit_count<=bit_count+1;
                  end
                end
              end
              DONE:begin
                s_done<=1;
                s_busy<=0;
                bit_count<=0;
                o_rx_data<=rx_shift;
                o_miso<= 1'bz;
                
              end
          endcase
          
        end
        
        
      end
endmodule
  
module spi_slave #(parameter size=8) (sclk,rst,ss,MOSI,MISO,ready,data_out);
input sclk,rst,ss; 
input MOSI;  
output reg MISO; //output to master
output reg ready; //ready means the data has fully received
output reg [size-1:0] data_out;
  reg [size-1:0] temp=8'b11000011;

  reg [$clog2(size)-1:0] count;
  


reg [1:0] state,next;
parameter idle=0,transfer=1,done=2;


//sequential block of fsm control
  always @(negedge sclk or negedge rst)begin
	if(rst)
		state<=idle;
	else
		state<=next;
end

always @(*)begin
      next=state;
      case(state)
        idle:next=(!ss)?transfer:idle;
        transfer:next=(count==size-1)?done:transfer;
        done:next=(!ss)?transfer:idle;
        default: next=idle;
	endcase

end

  always @(negedge sclk or negedge rst)begin
        if(rst)begin
              ready<=0;
              MISO<= 0;
              count<=0;
             end
    
        else begin 

             case(state)
                  idle:begin 
                    ready<=0;
                    count<=0;
                       if(!ss)
                              MISO <= temp[size-1]; 
                        end
                  transfer:begin 
                    MISO<=temp[size-2-count];
                    
                    if (count == size-1)begin
                            count<=count;
                    end
                          else
                             count<=count+1;
                         end
               done: begin count<=0; ready<=1;  end
               default:begin  
                             ready<=0;
                   end
                  endcase
        end

end



  always @(posedge sclk)begin
	if(rst)begin
		data_out<=0;
	end
  else if(state==transfer) begin
    data_out={data_out[size-2:0],MOSI};
		end
	else
		data_out<=data_out;
end


endmodule

Off_Chip_Protocols/SPI_Protocol/SPI_in_Mode_0/2_SPI_Master.v
module spi_master(
  input i_clk,    //system clock
  input i_rst,
  input start_en,  //signal to start the master
  input [7:0] i_tx_data,  //data to be transmitted to the slave
  input i_miso,
  
  output reg o_mosi,   //master out-slave in
  output reg cs,       //slave select
  output reg sclk,     //synchronized clock
  
  output reg m_busy,     //status of master
  output reg m_done,   
  
  output reg [7:0] rx_data
);
  
  reg [3:0] bit_count;
  reg [7:0] tx_shift;
  reg [7:0] rx_shift;
  
  reg [1:0] clk_count;
  reg sclk_enable;
  reg sclk_p; //for edge detection

  // ╔══════════════════════════════════════╗
  // ║       SCLK GENERATOR (INSIDE!)       ║
  // ╚══════════════════════════════════════╝
  always @(posedge i_clk) begin
        if (i_rst|| !sclk_enable)begin
            sclk<=1'b0;           
            clk_count<= 2'b0;
          end 
        else if(clk_count==2'd1)begin
            sclk<= ~sclk;        // Toggle every 4 sys_clk
            clk_count<=2'b0;
          end 
        else begin
            clk_count<=clk_count+1;
          end
    end
  
  
  reg [1:0] state,next;
  
  localparam IDLE=2'b00,
             LOAD=2'b01,
             TRANSFER=2'b10,
             DONE=2'b11;
  
 // ╔══════════════════════════════════════╗
 // ║  STATE TRANSITION SEQUENTIAL LOGIC   ║
 // ╚══════════════════════════════════════╝
  always @(posedge i_clk)begin
    if(i_rst)
      state<=IDLE;
    else
      state<=next;
  end
  
  
  
 // ╔══════════════════════════════════════╗
 // ║    NEXT STATE COMBINATIONAL LOGIC    ║
 // ╚══════════════════════════════════════╝
  always @(*)begin
    next=state;
    case(state)
           IDLE:next=start_en?LOAD:IDLE;
           LOAD:next=TRANSFER;
           TRANSFER:next=(bit_count==4'd8)?DONE:TRANSFER;
           DONE:next=IDLE;
           default:next=IDLE;
    endcase
  end
      
      always@(posedge i_clk)begin
        if(i_rst)begin
          bit_count<=0;
          tx_shift<=0;
          rx_shift<=0;
          sclk_enable<=0;
          sclk_p<=0;
          o_mosi<=0;
          cs<=1;
          sclk<=0;
          m_busy<=0;
          m_done<=0;
          rx_data<=0;
        end
        else begin
          sclk_p<=sclk;
          m_done <= 0;
          case(state)
              IDLE:begin
                bit_count<=0;
                sclk_enable<=0;
                cs<=1;
                m_busy<=0;
                m_done <= 0;
              end
              LOAD:begin
                cs<=0;                 //slave select is asserted
                tx_shift<=i_tx_data;  //loading the input data on a shift register
                rx_shift<=0;
                o_mosi<=i_tx_data[7]; //preloading of MSB before the sampling edge
                m_busy<=1;       // the master became busy
                bit_count<=0;   //making the count 0
                sclk_enable<=1;  //enabling the sclk generator
              end
              TRANSFER:begin
                
                if (sclk==1 && sclk_p==0)begin //rising edge
                  rx_shift<={rx_shift[6:0],i_miso};  //input from slave is sampled here
                 end
                
                
                if(sclk==0 && sclk_p==1)begin  //falling edge
                  if(bit_count<=7)begin
                    tx_shift<={tx_shift[6:0],1'b0};  //output to slave is changed here
                    o_mosi<=tx_shift[6];
                    bit_count<=bit_count+1;
                  end
                end
              end
              DONE:begin
                sclk_enable<=0;
                bit_count<=0;
                m_done<=1;
                m_busy<=0;
                rx_data<=rx_shift;
                o_mosi<=1'bz;
                
              end
          endcase
          
        end
        
        
      end
endmodule

Off_Chip_Protocols/SPI_Protocol/SPI_in_Mode_0/1_Top.v
module top (
    input  wire m_clk,      //Master clock
    input  wire s_clk,      //Slave clock  
    input  wire rst,        //Reset
    input  wire start_en,   //Start transfer enable for master
  
    input  wire [7:0] m_data_in,  //Master sending data
    input  wire [7:0] s_data_in,  //Slave sending data
  
    output wire [7:0] m_data_out, //Master received data
    output wire [7:0] s_data_out, //Slave received data
  
    output wire m_busy,     //Master busy
    output wire m_done,     //Master done
    output wire s_busy,     //Slave busy
    output wire s_done      //Slave done
);


wire sclk,cs;
wire MOSI,MISO;
  
  
//Master instantiation
  spi_master master_dut(.i_clk(m_clk),
                        .i_rst(rst),
                        .start_en(start_en),
                        .i_tx_data(m_data_in),
                        .i_miso(MISO),
                        .o_mosi(MOSI),
                        .cs(cs),
                        .sclk(sclk),
                        .m_busy(m_busy),
                        .m_done(m_done),
                        .rx_data(m_data_out));
  
  //slave instantiation
  spi_slave slave1(.i_clk(s_clk),
                   .sclk(sclk),
                   .cs(cs),
                   .i_mosi(MOSI),
                   .i_tx_data(s_data_in),
                   .o_miso(MISO),
                   .o_rx_data(s_data_out),
                   .s_done(s_done),
                   .s_busy(s_busy));
  

endmodule`include "3_SPI_Slave.v"
`include "2_SPI_Master.v"
module top #(parameter size=8)(clk,rst,en,data_in,finish,mdata_out,ready,data_out);
input clk,rst,en;
input [size-1:0] data_in; 
output finish,ready;
output [size-1:0] mdata_out,data_out;

wire sclk,ss;
wire MOSI,MISO;
  
  
//Master instantiation
  spi_master #(size) M(.clk(clk),
                        .rst(rst),
                        .en(en),
                        .data_in(data_in),
                        .MISO(MISO),
                        .MOSI(MOSI),
                        .ss(ss),
                        .finish(finish),
                        .sclk(sclk),
                        .mdata_out(mdata_out));
  
  spi_slave #(size) S1(.sclk(sclk),
                       .rst(rst),
                       .ss(ss),
                       .MOSI(MOSI),
                       .MISO(MISO),
                       .ready(ready),
                       .data_out(data_out));
endmodule

Off_Chip_Protocols/SPI_Protocol/SPI_in_Mode_0/Testbench.v
module tb_top;
    reg m_clk = 0, s_clk = 0, rst = 0, start_en = 0;
    reg [7:0] m_data_in;
    reg [7:0] s_data_in;
    
    wire [7:0] m_data_out, s_data_out;
    wire m_busy, m_done, s_busy, s_done;
    
    // Clock generation
    always #10 m_clk = ~m_clk;  // 50MHz Master's System clock
    always #5  s_clk = ~s_clk;  // 100MHz Slave's System clcok
    
    top dut (
        .m_clk(m_clk),
        .s_clk(s_clk),
        .rst(rst),
        .start_en(start_en),
        .m_data_in(m_data_in),
        .s_data_in(s_data_in),
        .m_data_out(m_data_out),
        .s_data_out(s_data_out),
        .m_busy(m_busy),
        .m_done(m_done),
        .s_busy(s_busy),
        .s_done(s_done)
    );
    
    initial begin
        $dumpfile("spi.vcd");
        $dumpvars(0, tb_top);
        
        // Test Case 1
        rst = 1; #20 rst= 0;
        #50 m_data_in=165; s_data_in=90;   start_en=1;
        wait(m_done==1); wait(s_done==1);
        $display("Test 1 - Master RX: %d (should be 90)", m_data_out);
        $display("Test 1 - Slave RX:  %d (should be 165)", s_data_out);
        
        // Test  2  
        m_data_in=16;  s_data_in=100;
        #40 wait(m_done==1); wait(s_done==1);
        
        $display("Test 2 - Master RX: %d (should be 100)", m_data_out);
        $display("Test 2 - Slave RX:  %d (should be 16)", s_data_out);
        
        // Test  3
        #40 m_data_in=33;  s_data_in=66;  
        wait(m_done==1); wait(s_done==1);
        $display("Test 3 - Master RX: %d (should be 66)", m_data_out);
        $display("Test 3 - Slave RX:  %d (should be 33)", s_data_out);
        
        // Test  4
        #40 m_data_in=255; s_data_in=0;   
        wait(m_done==1); wait(s_done==1);
        $display("Test 4 - Master RX: %d (should be 0)", m_data_out);
        $display("Test 4 - Slave RX:  %d (should be 255)", s_data_out);
        
        $display("=== ALL TESTS COMPLETE ===");
        $finish;
    end
endmodule

Off_Chip_Protocols/SPI_Protocol/SPI_in_Mode_0/spi.vcd
$date
	Sat Mar  7 00:36:29 2026
$end
$version
	Icarus Verilog
$end
$timescale
	1s
$end
$scope module tb_top $end
$var wire 1 ! s_done $end
$var wire 8 " s_data_out [7:0] $end
$var wire 1 # s_busy $end
$var wire 1 $ m_done $end
$var wire 8 % m_data_out [7:0] $end
$var wire 1 & m_busy $end
$var reg 1 ' m_clk $end
$var reg 8 ( m_data_in [7:0] $end
$var reg 1 ) rst $end
$var reg 1 * s_clk $end
$var reg 8 + s_data_in [7:0] $end
$var reg 1 , start_en $end
$scope module dut $end
$var wire 1 ' m_clk $end
$var wire 8 - m_data_in [7:0] $end
$var wire 1 ) rst $end
$var wire 1 * s_clk $end
$var wire 8 . s_data_in [7:0] $end
$var wire 1 , start_en $end
$var wire 1 / sclk $end
$var wire 1 ! s_done $end
$var wire 8 0 s_data_out [7:0] $end
$var wire 1 # s_busy $end
$var wire 1 $ m_done $end
$var wire 8 1 m_data_out [7:0] $end
$var wire 1 & m_busy $end
$var wire 1 2 cs $end
$var wire 1 3 MOSI $end
$var wire 1 4 MISO $end
$scope module master_dut $end
$var wire 1 ' i_clk $end
$var wire 1 ) i_rst $end
$var wire 8 5 i_tx_data [7:0] $end
$var wire 1 , start_en $end
$var wire 1 4 i_miso $end
$var parameter 2 6 DONE $end
$var parameter 2 7 IDLE $end
$var parameter 2 8 LOAD $end
$var parameter 2 9 TRANSFER $end
$var reg 4 : bit_count [3:0] $end
$var reg 2 ; clk_count [1:0] $end
$var reg 1 2 cs $end
$var reg 1 & m_busy $end
$var reg 1 $ m_done $end
$var reg 2 < next [1:0] $end
$var reg 1 3 o_mosi $end
$var reg 8 = rx_data [7:0] $end
$var reg 8 > rx_shift [7:0] $end
$var reg 1 / sclk $end
$var reg 1 ? sclk_enable $end
$var reg 1 @ sclk_p $end
$var reg 2 A state [1:0] $end
$var reg 8 B tx_shift [7:0] $end
$upscope $end
$scope module slave1 $end
$var wire 1 2 cs $end
$var wire 1 * i_clk $end
$var wire 1 3 i_mosi $end
$var wire 8 C i_tx_data [7:0] $end
$var wire 1 / sclk $end
$var parameter 2 D DONE $end
$var parameter 2 E IDLE $end
$var parameter 2 F LOAD $end
$var parameter 2 G TRANSFER $end
$var reg 4 H bit_count [3:0] $end
$var reg 2 I next [1:0] $end
$var reg 1 4 o_miso $end
$var reg 8 J o_rx_data [7:0] $end
$var reg 8 K rx_shift [7:0] $end
$var reg 1 # s_busy $end
$var reg 1 ! s_done $end
$var reg 1 L sclk_p $end
$var reg 2 M state [1:0] $end
$var reg 8 N tx_shift [7:0] $end
$upscope $end
$upscope $end
$upscope $end
$enddefinitions $end
$comment Show the parameter values. $end
$dumpall
b10 G
b1 F
b0 E
b11 D
b10 9
b1 8
b0 7
b11 6
$end
#0
$dumpvars
bx N
bx M
xL
bx K
bx J
bx I
bx H
bx C
bx B
bx A
x@
x?
bx >
bx =
b0 <
bx ;
bx :
bx 5
x4
x3
x2
bx 1
bx 0
x/
bx .
bx -
0,
bx +
0*
1)
bx (
0'
x&
bx %
x$
x#
bx "
x!
$end
#5
0!
1*
#10
b0 I
b0 ;
b0 A
b0 %
b0 1
b0 =
0$
0&
0/
12
03
0@
0?
b0 >
b0 B
b0 :
0*
1'
#15
b0 "
b0 0
b0 J
0#
z4
0L
b0 K
b0 N
b0 H
b0 M
1*
#20
0*
0'
0)
#25
1*
#30
0*
1'
#35
1*
#40
0*
0'
#45
1*
#50
0*
1'
#55
1*
#60
0*
0'
#65
1*
#70
b1 A
b10 <
0*
1'
1,
b1011010 +
b1011010 .
b1011010 C
b10100101 (
b10100101 -
b10100101 5
#75
1*
#80
0*
0'
#85
1*
#90
b1 I
b10 A
1?
1&
13
b10100101 B
02
0*
1'
#95
b10 I
b1 M
1*
#100
0*
0'
#105
b10 M
1#
04
b1011010 N
1*
#110
b1 ;
0*
1'
#115
1*
#120
0*
0'
#125
1*
#130
b0 ;
1/
0*
1'
#135
b1 K
1L
1*
#140
0*
0'
#145
1*
#150
1@
b1 ;
0*
1'
#155
1*
#160
0*
0'
#165
1*
#170
b0 ;
0/
0*
1'
#175
b1 H
14
b10110100 N
0L
1*
#180
0*
0'
#185
1*
#190
b1 :
03
b1001010 B
0@
b1 ;
0*
1'
#195
1*
#200
0*
0'
#205
1*
#210
b0 ;
1/
0*
1'
#215
b10 K
1L
1*
#220
0*
0'
#225
1*
#230
b1 >
1@
b1 ;
0*
1'
#235
1*
#240
0*
0'
#245
1*
#250
b0 ;
0/
0*
1'
#255
b10 H
04
b1101000 N
0L
1*
#260
0*
0'
#265
1*
#270
b10 :
13
b10010100 B
0@
b1 ;
0*
1'
#275
1*
#280
0*
0'
#285
1*
#290
b0 ;
1/
0*
1'
#295
b101 K
1L
1*
#300
0*
0'
#305
1*
#310
b10 >
1@
b1 ;
0*
1'
#315
1*
#320
0*
0'
#325
1*
#330
b0 ;
0/
0*
1'
#335
b11 H
14
b11010000 N
0L
1*
#340
0*
0'
#345
1*
#350
b11 :
03
b101000 B
0@
b1 ;
0*
1'
#355
1*
#360
0*
0'
#365
1*
#370
b0 ;
1/
0*
1'
#375
b1010 K
1L
1*
#380
0*
0'
#385
1*
#390
b101 >
1@
b1 ;
0*
1'
#395
1*
#400
0*
0'
#405
1*
#410
b0 ;
0/
0*
1'
#415
b100 H
b10100000 N
0L
1*
#420
0*
0'
#425
1*
#430
b100 :
b1010000 B
0@
b1 ;
0*
1'
#435
1*
#440
0*
0'
#445
1*
#450
b0 ;
1/
0*
1'
#455
b10100 K
1L
1*
#460
0*
0'
#465
1*
#470
b1011 >
1@
b1 ;
0*
1'
#475
1*
#480
0*
0'
#485
1*
#490
b0 ;
0/
0*
1'
#495
b101 H
04
b1000000 N
0L
1*
#500
0*
0'
#505
1*
#510
b101 :
13
b10100000 B
0@
b1 ;
0*
1'
#515
1*
#520
0*
0'
#525
1*
#530
b0 ;
1/
0*
1'
#535
b101001 K
1L
1*
#540
0*
0'
#545
1*
#550
b10110 >
1@
b1 ;
0*
1'
#555
1*
#560
0*
0'
#565
1*
#570
b0 ;
0/
0*
1'
#575
b110 H
14
b10000000 N
0L
1*
#580
0*
0'
#585
1*
#590
b110 :
03
b1000000 B
0@
b1 ;
0*
1'
#595
1*
#600
0*
0'
#605
1*
#610
b0 ;
1/
0*
1'
#615
b1010010 K
1L
1*
#620
0*
0'
#625
1*
#630
b101101 >
1@
b1 ;
0*
1'
#635
1*
#640
0*
0'
#645
1*
#650
b0 ;
0/
0*
1'
#655
b111 H
04
b0 N
0L
1*
#660
0*
0'
#665
1*
#670
b111 :
13
b10000000 B
0@
b1 ;
0*
1'
#675
1*
#680
0*
0'
#685
1*
#690
b0 ;
1/
0*
1'
#695
b10100101 K
1L
1*
#700
0*
0'
#705
1*
#710
b1011010 >
1@
b1 ;
0*
1'
#715
1*
#720
0*
0'
#725
1*
#730
b0 ;
0/
0*
1'
#735
b11 I
b1000 H
0L
1*
#740
0*
0'
#745
b11 M
1*
#750
b11 <
b1000 :
03
b0 B
0@
b1 ;
0*
1'
#755
z4
b10100101 "
b10100101 0
b10100101 J
b0 H
0#
1!
1*
#760
0*
0'
#765
1!
1*
#770
b0 <
b0 ;
1/
b11 A
0*
1'
#775
1!
1L
1*
#780
0*
0'
#785
1!
1*
#790
b1100100 +
b1100100 .
b1100100 C
b10000 (
b10000 -
b10000 5
b1 <
z3
b1011010 %
b1011010 1
b1011010 =
0&
1$
b0 :
0?
1@
b0 A
b1 ;
0*
1'
#795
1!
1*
#800
0*
0'
#805
1!
1*
#810
b10 <
b0 I
b0 ;
0/
b1 A
12
0$
0*
1'
#815
b0 "
b0 0
b0 J
0!
0L
b0 K
b0 M
1*
#820
0*
0'
#825
1*
#830
b1 I
1?
1&
03
b0 >
b10000 B
02
0@
b10 A
0*
1'
#835
b10 I
b1 M
1*
#840
0*
0'
#845
b10 M
1#
04
b1100100 N
1*
#850
b1 ;
0*
1'
#855
1*
#860
0*
0'
#865
1*
#870
b0 ;
1/
0*
1'
#875
1L
1*
#880
0*
0'
#885
1*
#890
b1 ;
1@
0*
1'
#895
1*
#900
0*
0'
#905
1*
#910
b0 ;
0/
0*
1'
#915
b1 H
14
b11001000 N
0L
1*
#920
0*
0'
#925
1*
#930
b1 ;
b1 :
b100000 B
0@
0*
1'
#935
1*
#940
0*
0'
#945
1*
#950
b0 ;
1/
0*
1'
#955
1L
1*
#960
0*
0'
#965
1*
#970
b1 ;
b1 >
1@
0*
1'
#975
1*
#980
0*
0'
#985
1*
#990
b0 ;
0/
0*
1'
#995
b10 H
b10010000 N
0L
1*
#1000
0*
0'
#1005
1*
#1010
b1 ;
b10 :
b1000000 B
0@
0*
1'
#1015
1*
#1020
0*
0'
#1025
1*
#1030
b0 ;
1/
0*
1'
#1035
1L
1*
#1040
0*
0'
#1045
1*
#1050
b1 ;
b11 >
1@
0*
1'
#1055
1*
#1060
0*
0'
#1065
1*
#1070
b0 ;
0/
0*
1'
#1075
b11 H
04
b100000 N
0L
1*
#1080
0*
0'
#1085
1*
#1090
b1 ;
b11 :
13
b10000000 B
0@
0*
1'
#1095
1*
#1100
0*
0'
#1105
1*
#1110
b0 ;
1/
0*
1'
#1115
b1 K
1L
1*
#1120
0*
0'
#1125
1*
#1130
b1 ;
b110 >
1@
0*
1'
#1135
1*
#1140
0*
0'
#1145
1*
#1150
b0 ;
0/
0*
1'
#1155
b100 H
b1000000 N
0L
1*
#1160
0*
0'
#1165
1*
#1170
b1 ;
b100 :
03
b0 B
0@
0*
1'
#1175
1*
#1180
0*
0'
#1185
1*
#1190
b0 ;
1/
0*
1'
#1195
b10 K
1L
1*
#1200
0*
0'
#1205
1*
#1210
b1 ;
b1100 >
1@
0*
1'
#1215
1*
#1220
0*
0'
#1225
1*
#1230
b0 ;
0/
0*
1'
#1235
b101 H
14
b10000000 N
0L
1*
#1240
0*
0'
#1245
1*
#1250
b1 ;
b101 :
0@
0*
1'
#1255
1*
#1260
0*
0'
#1265
1*
#1270
b0 ;
1/
0*
1'
#1275
b100 K
1L
1*
#1280
0*
0'
#1285
1*
#1290
b1 ;
b11001 >
1@
0*
1'
#1295
1*
#1300
0*
0'
#1305
1*
#1310
b0 ;
0/
0*
1'
#1315
b110 H
04
b0 N
0L
1*
#1320
0*
0'
#1325
1*
#1330
b1 ;
b110 :
0@
0*
1'
#1335
1*
#1340
0*
0'
#1345
1*
#1350
b0 ;
1/
0*
1'
#1355
b1000 K
1L
1*
#1360
0*
0'
#1365
1*
#1370
b1 ;
b110010 >
1@
0*
1'
#1375
1*
#1380
0*
0'
#1385
1*
#1390
b0 ;
0/
0*
1'
#1395
b111 H
0L
1*
#1400
0*
0'
#1405
1*
#1410
b1 ;
b111 :
0@
0*
1'
#1415
1*
#1420
0*
0'
#1425
1*
#1430
b0 ;
1/
0*
1'
#1435
b10000 K
1L
1*
#1440
0*
0'
#1445
1*
#1450
b1 ;
b1100100 >
1@
0*
1'
#1455
1*
#1460
0*
0'
#1465
1*
#1470
b0 ;
0/
0*
1'
#1475
b11 I
b1000 H
0L
1*
#1480
0*
0'
#1485
b11 M
1*
#1490
b11 <
b1 ;
b1000 :
0@
0*
1'
#1495
z4
b10000 "
b10000 0
b10000 J
b0 H
0#
1!
1*
#1500
0*
0'
#1505
1!
1*
#1510
b0 <
b11 A
b0 ;
1/
0*
1'
#1515
1!
1L
1*
#1520
0*
0'
#1525
1!
1*
#1530
b1 <
b1 ;
b0 A
z3
b1100100 %
b1100100 1
b1100100 =
0&
1$
b0 :
0?
1@
0*
1'
#1535
1!
1*
#1540
0*
0'
#1545
1!
1*
#1550
b0 I
b10 <
12
0$
b1 A
b0 ;
0/
0*
1'
#1555
b0 "
b0 0
b0 J
0!
0L
b0 K
b0 M
1*
#1560
0*
0'
#1565
1*
#1570
b1 I
b10 A
1?
1&
03
b0 >
b100001 B
02
0@
0*
1'
b1000010 +
b1000010 .
b1000010 C
b100001 (
b100001 -
b100001 5
#1575
b10 I
b1 M
1*
#1580
0*
0'
#1585
b10 M
1#
04
b1000010 N
1*
#1590
b1 ;
0*
1'
#1595
1*
#1600
0*
0'
#1605
1*
#1610
b0 ;
1/
0*
1'
#1615
1L
1*
#1620
0*
0'
#1625
1*
#1630
1@
b1 ;
0*
1'
#1635
1*
#1640
0*
0'
#1645
1*
#1650
b0 ;
0/
0*
1'
#1655
b1 H
14
b10000100 N
0L
1*
#1660
0*
0'
#1665
1*
#1670
b1 :
b1000010 B
0@
b1 ;
0*
1'
#1675
1*
#1680
0*
0'
#1685
1*
#1690
b0 ;
1/
0*
1'
#1695
1L
1*
#1700
0*
0'
#1705
1*
#1710
b1 >
1@
b1 ;
0*
1'
#1715
1*
#1720
0*
0'
#1725
1*
#1730
b0 ;
0/
0*
1'
#1735
b10 H
04
b1000 N
0L
1*
#1740
0*
0'
#1745
1*
#1750
b10 :
13
b10000100 B
0@
b1 ;
0*
1'
#1755
1*
#1760
0*
0'
#1765
1*
#1770
b0 ;
1/
0*
1'
#1775
b1 K
1L
1*
#1780
0*
0'
#1785
1*
#1790
b10 >
1@
b1 ;
0*
1'
#1795
1*
#1800
0*
0'
#1805
1*
#1810
b0 ;
0/
0*
1'
#1815
b11 H
b10000 N
0L
1*
#1820
0*
0'
#1825
1*
#1830
b11 :
03
b1000 B
0@
b1 ;
0*
1'
#1835
1*
#1840
0*
0'
#1845
1*
#1850
b0 ;
1/
0*
1'
#1855
b10 K
1L
1*
#1860
0*
0'
#1865
1*
#1870
b100 >
1@
b1 ;
0*
1'
#1875
1*
#1880
0*
0'
#1885
1*
#1890
b0 ;
0/
0*
1'
#1895
b100 H
b100000 N
0L
1*
#1900
0*
0'
#1905
1*
#1910
b100 :
b10000 B
0@
b1 ;
0*
1'
#1915
1*
#1920
0*
0'
#1925
1*
#1930
b0 ;
1/
0*
1'
#1935
b100 K
1L
1*
#1940
0*
0'
#1945
1*
#1950
b1000 >
1@
b1 ;
0*
1'
#1955
1*
#1960
0*
0'
#1965
1*
#1970
b0 ;
0/
0*
1'
#1975
b101 H
b1000000 N
0L
1*
#1980
0*
0'
#1985
1*
#1990
b101 :
b100000 B
0@
b1 ;
0*
1'
#1995
1*
#2000
0*
0'
#2005
1*
#2010
b0 ;
1/
0*
1'
#2015
b1000 K
1L
1*
#2020
0*
0'
#2025
1*
#2030
b10000 >
1@
b1 ;
0*
1'
#2035
1*
#2040
0*
0'
#2045
1*
#2050
b0 ;
0/
0*
1'
#2055
b110 H
14
b10000000 N
0L
1*
#2060
0*
0'
#2065
1*
#2070
b110 :
b1000000 B
0@
b1 ;
0*
1'
#2075
1*
#2080
0*
0'
#2085
1*
#2090
b0 ;
1/
0*
1'
#2095
b10000 K
1L
1*
#2100
0*
0'
#2105
1*
#2110
b100001 >
1@
b1 ;
0*
1'
#2115
1*
#2120
0*
0'
#2125
1*
#2130
b0 ;
0/
0*
1'
#2135
b111 H
04
b0 N
0L
1*
#2140
0*
0'
#2145
1*
#2150
b111 :
13
b10000000 B
0@
b1 ;
0*
1'
#2155
1*
#2160
0*
0'
#2165
1*
#2170
b0 ;
1/
0*
1'
#2175
b100001 K
1L
1*
#2180
0*
0'
#2185
1*
#2190
b1000010 >
1@
b1 ;
0*
1'
#2195
1*
#2200
0*
0'
#2205
1*
#2210
b0 ;
0/
0*
1'
#2215
b11 I
b1000 H
0L
1*
#2220
0*
0'
#2225
b11 M
1*
#2230
b11 <
b1000 :
03
b0 B
0@
b1 ;
0*
1'
#2235
z4
b100001 "
b100001 0
b100001 J
b0 H
0#
1!
1*
#2240
0*
0'
#2245
1!
1*
#2250
b0 <
b0 ;
1/
b11 A
0*
1'
#2255
1!
1L
1*
#2260
0*
0'
#2265
1!
1*
#2270
b1 <
z3
b1000010 %
b1000010 1
b1000010 =
0&
1$
b0 :
0?
1@
b0 A
b1 ;
0*
1'
#2275
1!
1*
#2280
0*
0'
#2285
1!
1*
#2290
b10 <
b0 I
b0 ;
0/
b1 A
12
0$
0*
1'
#2295
b0 "
b0 0
b0 J
0!
0L
b0 K
b0 M
1*
#2300
0*
0'
#2305
1*
#2310
b1 I
1?
1&
13
b0 >
b11111111 B
02
0@
b10 A
0*
1'
b0 +
b0 .
b0 C
b11111111 (
b11111111 -
b11111111 5
#2315
b10 I
b1 M
1*
#2320
0*
0'
#2325
b10 M
1#
04
1*
#2330
b1 ;
0*
1'
#2335
1*
#2340
0*
0'
#2345
1*
#2350
b0 ;
1/
0*
1'
#2355
b1 K
1L
1*
#2360
0*
0'
#2365
1*
#2370
b1 ;
1@
0*
1'
#2375
1*
#2380
0*
0'
#2385
1*
#2390
b0 ;
0/
0*
1'
#2395
b1 H
0L
1*
#2400
0*
0'
#2405
1*
#2410
b1 ;
b1 :
b11111110 B
0@
0*
1'
#2415
1*
#2420
0*
0'
#2425
1*
#2430
b0 ;
1/
0*
1'
#2435
b11 K
1L
1*
#2440
0*
0'
#2445
1*
#2450
b1 ;
1@
0*
1'
#2455
1*
#2460
0*
0'
#2465
1*
#2470
b0 ;
0/
0*
1'
#2475
b10 H
0L
1*
#2480
0*
0'
#2485
1*
#2490
b1 ;
b10 :
b11111100 B
0@
0*
1'
#2495
1*
#2500
0*
0'
#2505
1*
#2510
b0 ;
1/
0*
1'
#2515
b111 K
1L
1*
#2520
0*
0'
#2525
1*
#2530
b1 ;
1@
0*
1'
#2535
1*
#2540
0*
0'
#2545
1*
#2550
b0 ;
0/
0*
1'
#2555
b11 H
0L
1*
#2560
0*
0'
#2565
1*
#2570
b1 ;
b11 :
b11111000 B
0@
0*
1'
#2575
1*
#2580
0*
0'
#2585
1*
#2590
b0 ;
1/
0*
1'
#2595
b1111 K
1L
1*
#2600
0*
0'
#2605
1*
#2610
b1 ;
1@
0*
1'
#2615
1*
#2620
0*
0'
#2625
1*
#2630
b0 ;
0/
0*
1'
#2635
b100 H
0L
1*
#2640
0*
0'
#2645
1*
#2650
b1 ;
b100 :
b11110000 B
0@
0*
1'
#2655
1*
#2660
0*
0'
#2665
1*
#2670
b0 ;
1/
0*
1'
#2675
b11111 K
1L
1*
#2680
0*
0'
#2685
1*
#2690
b1 ;
1@
0*
1'
#2695
1*
#2700
0*
0'
#2705
1*
#2710
b0 ;
0/
0*
1'
#2715
b101 H
0L
1*
#2720
0*
0'
#2725
1*
#2730
b1 ;
b101 :
b11100000 B
0@
0*
1'
#2735
1*
#2740
0*
0'
#2745
1*
#2750
b0 ;
1/
0*
1'
#2755
b111111 K
1L
1*
#2760
0*
0'
#2765
1*
#2770
b1 ;
1@
0*
1'
#2775
1*
#2780
0*
0'
#2785
1*
