Off_Chip_Protocols/SPI_Protocol/SPI_All_Four_Modes/3_SPI_Slave.v
module spi_slave  #(parameter MODE=2'b00)(
  input i_clk,     //system clock of slave
  input sclk,       //synchronous clock from master
  input cs,          //slave select
  input i_mosi,
  input [7:0] i_tx_data,    //data which is to be send to master
  
  output reg o_miso,
  output reg [7:0] o_rx_data,   //data received from master
  output reg s_done,
  output reg s_busy

);
  
  
  //MODE parameters
  wire CPOL;
  wire CPHA;
  
  assign CPOL=MODE[1];
  assign CPHA=MODE[0];
  
  wire sample_edge0,shift_edge0,sample_edge1,shift_edge1;
  wire rising_edge,falling_edge;
  wire sample_edge,shift_edge;
  
  assign rising_edge=(sclk==1 && sclk_p==0);
  assign falling_edge=(sclk==0 && sclk_p==1);
  
  assign sample_edge0=(CPOL==0 && CPHA==0)?rising_edge:falling_edge;
  assign shift_edge0=(CPOL==0 && CPHA==0)?falling_edge:rising_edge;
  
  assign sample_edge1=(CPOL==1 && CPHA==0)?falling_edge:rising_edge;
  assign shift_edge1=(CPOL==1 && CPHA==0)?rising_edge:falling_edge;
  
  assign sample_edge= (CPOL)?sample_edge1:sample_edge0;
  assign shift_edge= (CPOL)?shift_edge1:shift_edge0;
  
  
  //shift registers
  reg [7:0] tx_shift;
  reg [7:0] rx_shift;
  
  reg sclk_p;
  reg [3:0] bit_count;
  
  reg [1:0] state,next;
  localparam IDLE=2'b00,
             LOAD=2'b01,
             TRANSFER=2'b10,
             DONE=2'b11;
  
  always@(posedge i_clk)begin
    if(cs)
      state<=IDLE;
    else
      state<=next;
  end
  
  
  //next state combinational logic
  always @(*)begin
    next=state;
    case(state)
           IDLE:next=(cs==0)?LOAD:IDLE;
           LOAD:next=TRANSFER;
           TRANSFER:next=(bit_count==4'd8)?DONE:TRANSFER;
           DONE:next=(!cs)?DONE:IDLE;
           default:next=IDLE;
    endcase
  end
      
       always@(posedge i_clk)begin
         sclk_p<=sclk;
         if(cs)begin
          bit_count<=0;
          tx_shift<=0;
          rx_shift<=0;
          sclk_p<=0;
          o_miso<=1'bz;
          s_busy<=0;
          s_done<=0;
          o_rx_data<=0;
        end
        else begin
          s_done <= 0; 
          
          case(state)
              IDLE:begin
                bit_count<=0;
                s_busy<=0;
                o_miso<=1'bz;
              end
              LOAD:begin               
                tx_shift<=i_tx_data;  //loading the input data(to be sent) on a shift register
                rx_shift<=0;
               // o_miso<=i_tx_data[7]; //preloading of MSB before the sampling edge
                s_busy<=1;       // the master became busy
                bit_count<=0;   //making the count 0
                if(CPHA==0)
                       o_miso <= i_tx_data[7];   // preload only for CPHA=0
              end
              TRANSFER:begin
                
                if (sample_edge)begin 
                  rx_shift<={rx_shift[6:0],i_mosi};  //input from slave is sampled here
                 end
                
                if(shift_edge) begin 
                  if(bit_count < 8 && CPHA==0) 
                    bit_count <= bit_count + 1; 
                  
                end 
                if(sample_edge) begin 
                  if(bit_count < 8 && CPHA==1) 
                    bit_count <= bit_count + 1; 
                end
                
                if(shift_edge)begin  
                  if(bit_count<=7)begin
                    if(CPHA && bit_count == 0)
                            o_miso <= tx_shift[7];
                    else begin
                            tx_shift <= {tx_shift[6:0],1'b0};
                            o_miso  <= tx_shift[6];
                    end
                  end
                end
              end
              DONE:begin
                s_done<=1;
                s_busy<=0;
                bit_count<=0;
                o_rx_data<=rx_shift;
                o_miso<= 1'bz;
                
              end
          endcase
          
        end
        
        
      end
endmodule

Off_Chip_Protocols/SPI_Protocol/SPI_All_Four_Modes/2_SPI_Master.v
module spi_master #(parameter MODE=2'b00) (
  input i_clk,    //system clock
  input i_rst,
  input start_en,  //signal to start the master
  input [7:0] i_tx_data,  //data to be transmitted to the slave
  input i_miso,
  
  output reg o_mosi,   //master out-slave in
  output reg cs,       //slave select
  output reg sclk,     //synchronized clock
  
  output reg m_busy,     //status of master
  output reg m_done,   
  
  output reg [7:0] rx_data
);
  
  reg [3:0] bit_count;
  reg [7:0] tx_shift;
  reg [7:0] rx_shift;
  
  reg [1:0] clk_count;
  reg sclk_enable;
  reg sclk_p; //for edge detection
  
  //MODE parameters
  wire CPOL;
  wire CPHA;
  
  assign CPOL=MODE[1];
  assign CPHA=MODE[0];
  
  wire sample_edge0,shift_edge0,sample_edge1,shift_edge1;
  wire rising_edge,falling_edge;
  wire sample_edge,shift_edge;
  
  assign rising_edge=(sclk==1 && sclk_p==0);
  assign falling_edge=(sclk==0 && sclk_p==1);
  
  assign sample_edge0=(CPOL==0 && CPHA==0)?rising_edge:falling_edge;
  assign shift_edge0=(CPOL==0 && CPHA==0)?falling_edge:rising_edge;
  
  assign sample_edge1=(CPOL==1 && CPHA==0)?falling_edge:rising_edge;
  assign shift_edge1=(CPOL==1 && CPHA==0)?rising_edge:falling_edge;
  
  assign sample_edge= (CPOL)?sample_edge1:sample_edge0;
  assign shift_edge= (CPOL)?shift_edge1:shift_edge0;

  // ╔══════════════════════════════════════╗
  // ║       SCLK GENERATOR (INSIDE!)       ║
  // ╚══════════════════════════════════════╝
  always @(posedge i_clk) begin
        if (i_rst|| !sclk_enable)begin
            sclk<=CPOL;           
            clk_count<= 2'b0;
          end 
        else if(clk_count==2'd1)begin
            sclk<= ~sclk;        // Toggle every 4 sys_clk
            clk_count<=2'b0;
          end 
        else begin
            clk_count<=clk_count+1;
          end
    end
  
  
  reg [1:0] state,next;
  
  localparam IDLE=2'b00,
             LOAD=2'b01,
             TRANSFER=2'b10,
             DONE=2'b11;
  
 // ╔══════════════════════════════════════╗
 // ║  state transition sequential logic   ║
 // ╚══════════════════════════════════════╝
  always @(posedge i_clk)begin
    if(i_rst)
      state<=IDLE;
    else
      state<=next;
  end
  
  
  //next state combinational logic
  always @(*)begin
    next=state;
    case(state)
           IDLE:next=start_en?LOAD:IDLE;
           LOAD:next=TRANSFER;
           TRANSFER:next=(bit_count==4'd8)?DONE:TRANSFER;
           DONE:next=IDLE;
           default:next=IDLE;
    endcase
  end
      
      always@(posedge i_clk)begin
        sclk_p <= sclk; 
        if(i_rst)begin
          bit_count<=0;
          tx_shift<=0;
          rx_shift<=0;
          sclk_enable<=0;
          sclk_p<=0;
          o_mosi<=0;
          cs<=1;
          sclk<=0;
          m_busy<=0;
          m_done<=0;
          rx_data<=0;
        end
        else begin
          m_done <= 0;
          case(state)
              IDLE:begin
                bit_count<=0;
                sclk_enable<=0;
                cs<=1;
                m_busy<=0;
                m_done <= 0;
              end
              LOAD:begin
                cs<=0;                 //slave select is asserted
                tx_shift<=i_tx_data;  //loading the input data on a shift register
                rx_shift<=0;
                //o_mosi<=i_tx_data[7]; //preloading of MSB before the sampling edge
                m_busy<=1;       // the master became busy
                bit_count<=0;   //making the count 0
                sclk_enable<=1;  //enabling the sclk generator
                if(CPHA==0)
                       o_mosi <= i_tx_data[7];   // preload only for CPHA=0
              end
              TRANSFER:begin
                
                if (sample_edge)begin //rising edge
                  rx_shift<={rx_shift[6:0],i_miso};  //input from slave is sampled here
                 end
                
                                
                if(shift_edge) begin 
                  if(bit_count < 8 && CPHA==0) 
                    bit_count <= bit_count + 1; 
                  
                end 
                if(sample_edge) begin 
                  if(bit_count < 8 && CPHA==1) 
                    bit_count <= bit_count + 1; 
                end
                
                if(shift_edge)begin  //falling edge
                  if(bit_count<=7)begin
                    if(CPHA && bit_count == 0)
                            o_mosi <= tx_shift[7];
                    else begin
                            tx_shift <= {tx_shift[6:0],1'b0};
                            o_mosi  <= tx_shift[6];
                    end
                    
                  end
                end
              end
              DONE:begin
                sclk_enable<=0;
                bit_count<=0;
                m_done<=1;
                m_busy<=0;
                rx_data<=rx_shift;
                o_mosi<=1'bz;
                
              end
          endcase
          
        end
        
        
      end
endmodule

Off_Chip_Protocols/SPI_Protocol/SPI_All_Four_Modes/1_Top.v
`include "2_SPI_Master.v"
`include "3_SPI_Slave.v"
module top #(parameter MODE=2'b00)(
    input  wire m_clk,      //Master clock
    input  wire s_clk,      //Slave clock  
    input  wire rst,        //Reset
    input  wire start_en,   //Start transfer enable for master
  
    input  wire [7:0] m_data_in,  //Master sending data
    input  wire [7:0] s_data_in,  //Slave sending data
  
    output wire [7:0] m_data_out, //Master received data
    output wire [7:0] s_data_out, //Slave received data
  
    output wire m_busy,     //Master busy
    output wire m_done,     //Master done
    output wire s_busy,     //Slave busy
    output wire s_done      //Slave done
);


wire sclk,cs;
wire MOSI,MISO;
  

  
  
//Master instantiation
  spi_master #(MODE) master_dut(.i_clk(m_clk),
                        .i_rst(rst),
                        .start_en(start_en),
                        .i_tx_data(m_data_in),
                        .i_miso(MISO),
                        .o_mosi(MOSI),
                        .cs(cs),
                        .sclk(sclk),
                        .m_busy(m_busy),
                        .m_done(m_done),
                        .rx_data(m_data_out));
  
  //slave instantiation
  spi_slave #(MODE) slave1(.i_clk(s_clk),
                   .sclk(sclk),
                   .cs(cs),
                   .i_mosi(MOSI),
                   .i_tx_data(s_data_in),
                   .o_miso(MISO),
                   .o_rx_data(s_data_out),
                   .s_done(s_done),
                   .s_busy(s_busy));
  

endmodule

Off_Chip_Protocols/SPI_Protocol/SPI_All_Four_Modes/TestBench.v
module tb_top #(parameter MODE=2'b11);
    reg m_clk,s_clk,rst,start_en;
    reg [7:0] m_data_in;
    reg [7:0] s_data_in;
    
    wire [7:0] m_data_out, s_data_out;
    wire m_busy, m_done, s_busy, s_done;
    
    // Clock generation
    always #10 m_clk=~m_clk;  // 50MHz
    always #5  s_clk=~s_clk;  // 100MHz
    
  top #(MODE) dut (
        .m_clk(m_clk),
        .s_clk(s_clk),
        .rst(rst),
        .start_en(start_en),
        .m_data_in(m_data_in),
        .s_data_in(s_data_in),
        .m_data_out(m_data_out),
        .s_data_out(s_data_out),
        .m_busy(m_busy),
        .m_done(m_done),
        .s_busy(s_busy),
        .s_done(s_done)
    );
    
    initial begin
        m_clk=0;s_clk=0;start_en=0;
        $dumpfile("spi.vcd");
        $dumpvars(0, tb_top);
        
        // Test Case 1
        rst = 1; #20 rst = 0;
        #50 m_data_in=165; s_data_in=90;   start_en=1;
        wait(m_done==1); wait(s_done==1);
        $display("\n\n*****Multiple Data - SIngle Start Enable TEST SERIES*****");
        $display("Test 1 - Master RX: %d (should be 90)", m_data_out);
        $display("Test 1 - Slave RX:  %d (should be 165)", s_data_out);
        
        // Test  2  
        m_data_in=16;  s_data_in=100;
        #40 wait(m_done==1); wait(s_done==1);
        
        $display("Test 2 - Master RX: %d (should be 100)", m_data_out);
        $display("Test 2 - Slave RX:  %d (should be 16)", s_data_out);
        
        // Test  3
        #40 m_data_in=33;  s_data_in=66;  
        wait(m_done==1); wait(s_done==1);
        $display("Test 3 - Master RX: %d (should be 66)", m_data_out);
        $display("Test 3 - Slave RX:  %d (should be 33)", s_data_out);
        
        // Test  4
        #40 m_data_in=27; s_data_in=0; #50 start_en=0;  
        wait(m_done==1); wait(s_done==1);
        $display("Test 4 - Master RX: %d (should be 0)", m_data_out);
      $display("Test 4 - Slave RX:  %d (should be 27)", s_data_out);
        
        $display("=== TESTS COMPLETE ===");
        // Test Case 1 
        #50 m_data_in=55; s_data_in=9; 
        start_en=1;#50 start_en=0;
        wait(m_done==1); wait(s_done==1);
        $display("\n\n*****Multiple Data - Multiple Start Enables TEST SERIES*****");
        $display("Test 1 - Master RX: %d (should be 9)", m_data_out);
        $display("Test 1 - Slave RX:  %d (should be 55)", s_data_out);
        
        // Test  2  
        #50 m_data_in=123;  s_data_in = 108;  
        start_en=1; #50 start_en = 0;
        wait(m_done==1); wait(s_done==1);
        $display("Test 2 - Master RX: %d (should be 108)", m_data_out);
        $display("Test 2 - Slave RX:  %d (should be 123)", s_data_out);
        
        // Test  3
        #50 m_data_in=42;  s_data_in=89;   
        start_en=1; #50 start_en=0;
        wait(m_done==1); wait(s_done==1);
        $display("Test 3 - Master RX: %d (should be 89)", m_data_out);
        $display("Test 3 - Slave RX:  %d (should be 42)", s_data_out);
        wait(m_done==0); wait(s_done==0);

        
        // Test  4
        m_data_in=200; s_data_in=0;
        start_en=1; #50 start_en= 0;
        wait(m_done==1); wait(s_done==1);
        $display("Test 4 - Master RX: %d (should be 0)", m_data_out);
        $display("Test 4 - Slave RX:  %d (should be 200)", s_data_out);
        
      $display("************ ALL TESTS COMPLETE **************");
        $finish;
    end
endmodule

Off_Chip_Protocols/SPI_Protocol/SPI_All_Four_Modes/spi.vcd
$date
	Sat Mar  7 14:01:37 2026
$end
$version
	Icarus Verilog
$end
$timescale
	1s
$end
$scope module tb_top $end
$var wire 1 ! s_done $end
$var wire 8 " s_data_out [7:0] $end
$var wire 1 # s_busy $end
$var wire 1 $ m_done $end
$var wire 8 % m_data_out [7:0] $end
$var wire 1 & m_busy $end
$var parameter 2 ' MODE $end
$var reg 1 ( m_clk $end
$var reg 8 ) m_data_in [7:0] $end
$var reg 1 * rst $end
$var reg 1 + s_clk $end
$var reg 8 , s_data_in [7:0] $end
$var reg 1 - start_en $end
$scope module dut $end
$var wire 1 ( m_clk $end
$var wire 8 . m_data_in [7:0] $end
$var wire 1 * rst $end
$var wire 1 + s_clk $end
$var wire 8 / s_data_in [7:0] $end
$var wire 1 - start_en $end
$var wire 1 0 sclk $end
$var wire 1 ! s_done $end
$var wire 8 1 s_data_out [7:0] $end
$var wire 1 # s_busy $end
$var wire 1 $ m_done $end
$var wire 8 2 m_data_out [7:0] $end
$var wire 1 & m_busy $end
$var wire 1 3 cs $end
$var wire 1 4 MOSI $end
$var wire 1 5 MISO $end
$var parameter 2 6 MODE $end
$scope module master_dut $end
$var wire 1 7 CPHA $end
$var wire 1 8 CPOL $end
$var wire 1 9 falling_edge $end
$var wire 1 ( i_clk $end
$var wire 1 * i_rst $end
$var wire 8 : i_tx_data [7:0] $end
$var wire 1 ; rising_edge $end
$var wire 1 < sample_edge $end
$var wire 1 = shift_edge $end
$var wire 1 - start_en $end
$var wire 1 > shift_edge1 $end
$var wire 1 ? shift_edge0 $end
$var wire 1 @ sample_edge1 $end
$var wire 1 A sample_edge0 $end
$var wire 1 5 i_miso $end
$var parameter 2 B DONE $end
$var parameter 2 C IDLE $end
$var parameter 2 D LOAD $end
$var parameter 2 E MODE $end
$var parameter 2 F TRANSFER $end
$var reg 4 G bit_count [3:0] $end
$var reg 2 H clk_count [1:0] $end
$var reg 1 3 cs $end
$var reg 1 & m_busy $end
$var reg 1 $ m_done $end
$var reg 2 I next [1:0] $end
$var reg 1 4 o_mosi $end
$var reg 8 J rx_data [7:0] $end
$var reg 8 K rx_shift [7:0] $end
$var reg 1 0 sclk $end
$var reg 1 L sclk_enable $end
$var reg 1 M sclk_p $end
$var reg 2 N state [1:0] $end
$var reg 8 O tx_shift [7:0] $end
$upscope $end
$scope module slave1 $end
$var wire 1 P CPHA $end
$var wire 1 Q CPOL $end
$var wire 1 3 cs $end
$var wire 1 R falling_edge $end
$var wire 1 + i_clk $end
$var wire 1 4 i_mosi $end
$var wire 8 S i_tx_data [7:0] $end
$var wire 1 T rising_edge $end
$var wire 1 U sample_edge $end
$var wire 1 0 sclk $end
$var wire 1 V shift_edge $end
$var wire 1 W shift_edge1 $end
$var wire 1 X shift_edge0 $end
$var wire 1 Y sample_edge1 $end
$var wire 1 Z sample_edge0 $end
$var parameter 2 [ DONE $end
$var parameter 2 \ IDLE $end
$var parameter 2 ] LOAD $end
$var parameter 2 ^ MODE $end
$var parameter 2 _ TRANSFER $end
$var reg 4 ` bit_count [3:0] $end
$var reg 2 a next [1:0] $end
$var reg 1 5 o_miso $end
$var reg 8 b o_rx_data [7:0] $end
$var reg 8 c rx_shift [7:0] $end
$var reg 1 # s_busy $end
$var reg 1 ! s_done $end
$var reg 1 d sclk_p $end
$var reg 2 e state [1:0] $end
$var reg 8 f tx_shift [7:0] $end
$upscope $end
$upscope $end
$upscope $end
$enddefinitions $end
$comment Show the parameter values. $end
$dumpall
b10 _
b11 ^
b1 ]
b0 \
b11 [
b10 F
b11 E
b1 D
b0 C
b11 B
b11 6
b11 '
$end
#0
$dumpvars
bx f
bx e
xd
bx c
bx b
bx a
bx `
xZ
xY
xX
xW
xV
xU
xT
bx S
xR
1Q
1P
bx O
bx N
xM
xL
bx K
bx J
b0 I
bx H
bx G
xA
x@
x?
x>
x=
x<
x;
bx :
x9
18
17
x5
x4
x3
bx 2
bx 1
x0
bx /
bx .
0-
bx ,
0+
1*
bx )
0(
x&
bx %
x$
x#
bx "
x!
$end
#5
0!
1+
#10
0Z
0V
0W
1?
1<
1@
0A
0=
0>
0R
b0 a
1;
09
b0 H
b0 N
b0 %
b0 2
b0 J
0$
0&
10
13
04
0M
0L
b0 K
b0 O
b0 G
0+
1(
#15
1X
1U
1Y
1T
b0 "
b0 1
b0 b
0#
z5
b0 c
b0 f
b0 `
0d
b0 e
1+
#20
0+
0(
0*
#25
0d
1+
#30
0?
0<
0@
0;
1M
0+
1(
#35
0d
1+
#40
0+
0(
#45
0d
1+
#50
0+
1(
#55
0d
1+
#60
0+
0(
#65
0d
1+
#70
b1 N
b10 I
0+
1(
1-
b1011010 ,
b1011010 /
b1011010 S
b10100101 )
b10100101 .
b10100101 :
#75
0d
1+
#80
0+
0(
#85
0d
1+
#90
b1 a
b10 N
1L
1&
b10100101 O
03
0+
1(
#95
0X
0U
0Y
0T
b10 a
1d
b1 e
1+
#100
0+
0(
#105
b10 e
1#
b1011010 f
1+
#110
b1 H
0+
1(
#115
1+
#120
0+
0(
#125
1+
#130
1A
1=
1>
1Z
1V
1W
19
1R
b0 H
00
0+
1(
#135
0Z
0V
0W
0R
05
0d
1+
#140
0+
0(
#145
1+
#150
0A
0=
0>
09
14
0M
b1 H
0+
1(
#155
1+
#160
0+
0(
#165
1+
#170
1?
1<
1@
1X
1U
1Y
1;
1T
b0 H
10
0+
1(
#175
0X
0U
0Y
0T
b1 `
b1 c
1d
1+
#180
0+
0(
#185
1+
#190
0?
0<
0@
0;
b1 G
1M
b1 H
0+
1(
#195
1+
#200
0+
0(
#205
1+
#210
1A
1=
1>
1Z
1V
1W
19
1R
b0 H
00
0+
1(
#215
0Z
0V
0W
0R
15
b10110100 f
0d
1+
#220
0+
0(
#225
1+
#230
0A
0=
0>
09
04
b1001010 O
0M
b1 H
0+
1(
#235
1+
#240
0+
0(
#245
1+
#250
1?
1<
1@
1X
1U
1Y
1;
1T
b0 H
10
0+
1(
#255
0X
0U
0Y
0T
b10 `
b10 c
1d
1+
#260
0+
0(
#265
1+
#270
0?
0<
0@
0;
b10 G
b1 K
1M
b1 H
0+
1(
#275
1+
#280
0+
0(
#285
1+
#290
1A
1=
1>
1Z
1V
1W
19
1R
b0 H
00
0+
1(
#295
0Z
0V
0W
0R
05
b1101000 f
0d
1+
#300
0+
0(
#305
1+
#310
0A
0=
0>
09
14
b10010100 O
0M
b1 H
0+
1(
#315
1+
#320
0+
0(
#325
1+
#330
1?
1<
1@
1X
1U
1Y
1;
1T
b0 H
10
0+
1(
#335
0X
0U
0Y
0T
b11 `
b101 c
1d
1+
#340
0+
0(
#345
1+
#350
0?
0<
0@
0;
b11 G
b10 K
1M
b1 H
0+
1(
#355
1+
#360
0+
0(
#365
1+
#370
1A
1=
1>
1Z
1V
1W
19
1R
b0 H
00
0+
1(
#375
0Z
0V
0W
0R
15
b11010000 f
0d
1+
#380
0+
0(
#385
1+
#390
0A
0=
0>
09
04
b101000 O
0M
b1 H
0+
1(
#395
1+
#400
0+
0(
#405
1+
#410
1?
1<
1@
1X
1U
1Y
1;
1T
b0 H
10
0+
1(
#415
0X
0U
0Y
0T
b100 `
b1010 c
1d
1+
#420
0+
0(
#425
1+
#430
0?
0<
0@
0;
b100 G
b101 K
1M
b1 H
0+
1(
#435
1+
#440
0+
0(
#445
1+
#450
1A
1=
1>
1Z
1V
1W
19
1R
b0 H
00
0+
1(
#455
0Z
0V
0W
0R
b10100000 f
0d
1+
#460
0+
0(
#465
1+
#470
0A
0=
0>
09
b1010000 O
0M
b1 H
0+
1(
#475
1+
#480
0+
0(
#485
1+
#490
1?
1<
1@
1X
1U
1Y
1;
1T
b0 H
10
0+
1(
#495
0X
0U
0Y
0T
b101 `
b10100 c
1d
1+
#500
0+
0(
#505
1+
#510
0?
0<
0@
0;
b101 G
b1011 K
1M
b1 H
0+
1(
#515
1+
#520
0+
0(
#525
1+
#530
1A
1=
1>
1Z
1V
1W
19
1R
b0 H
00
0+
1(
#535
0Z
0V
0W
0R
05
b1000000 f
0d
1+
#540
0+
0(
#545
1+
#550
0A
0=
0>
09
14
b10100000 O
0M
b1 H
0+
1(
#555
1+
#560
0+
0(
#565
1+
#570
1?
1<
1@
1X
1U
1Y
1;
1T
b0 H
10
0+
1(
#575
0X
0U
0Y
0T
b110 `
b101001 c
1d
1+
#580
0+
0(
#585
1+
#590
0?
0<
0@
0;
b110 G
b10110 K
1M
b1 H
0+
1(
#595
1+
#600
0+
0(
#605
1+
#610
1A
1=
1>
1Z
1V
1W
19
1R
b0 H
00
0+
1(
#615
0Z
0V
0W
0R
15
b10000000 f
0d
1+
#620
0+
0(
#625
1+
#630
0A
0=
0>
09
04
b1000000 O
0M
b1 H
0+
1(
#635
1+
#640
0+
0(
#645
1+
#650
1?
1<
1@
1X
1U
1Y
1;
1T
b0 H
10
0+
1(
#655
0X
0U
0Y
0T
b111 `
b1010010 c
1d
1+
#660
0+
0(
#665
1+
#670
0?
0<
0@
0;
b111 G
b101101 K
1M
b1 H
0+
1(
#675
1+
#680
0+
0(
#685
1+
#690
1A
1=
1>
1Z
1V
1W
19
1R
b0 H
00
0+
1(
#695
0Z
0V
0W
0R
05
b0 f
0d
1+
#700
0+
0(
#705
1+
#710
0A
0=
0>
09
14
b10000000 O
0M
b1 H
0+
1(
#715
1+
#720
0+
0(
#725
1+
#730
1?
1<
1@
1X
1U
1Y
1;
1T
b0 H
10
0+
1(
#735
0X
0U
0Y
b11 a
0T
b1000 `
b10100101 c
1d
1+
#740
0+
0(
#745
b11 e
1+
#750
0?
0<
0@
b11 I
0;
b1000 G
b1011010 K
1M
b1 H
0+
1(
#755
z5
b10100101 "
b10100101 1
b10100101 b
b0 `
0#
1!
1+
#760
0+
0(
#765
1!
1+
#770
1A
1=
1>
1Z
1V
1W
19
1R
b0 I
b0 H
00
b11 N
0+
1(
#775
0Z
0V
0W
0R
1!
0d
1+
#780
0+
0(
#785
1!
1+
#790
0A
0=
0>
b1100100 ,
b1100100 /
b1100100 S
b10000 )
b10000 .
b10000 :
09
b1 I
z4
b1011010 %
b1011010 2
b1011010 J
0&
1$
b0 G
0L
0M
b0 N
b1 H
0+
1(
#795
1!
1+
#800
0+
0(
#805
1!
1+
#810
1?
1<
1@
1X
1U
1Y
1;
1T
b10 I
b0 a
b0 H
10
b1 N
13
0$
0+
1(
#815
b0 "
b0 1
b0 b
0!
b0 c
0d
b0 e
1+
#820
0+
0(
#825
0d
1+
#830
0?
0<
0@
b1 a
0;
1L
1&
b0 K
b10000 O
03
1M
b10 N
0+
1(
#835
0X
0U
0Y
0T
b10 a
1d
b1 e
1+
#840
0+
0(
#845
b10 e
1#
b1100100 f
1+
#850
b1 H
0+
1(
#855
1+
#860
0+
0(
#865
1+
#870
1A
1=
1>
1Z
1V
1W
19
1R
b0 H
00
0+
1(
#875
0Z
0V
0W
0R
05
0d
1+
#880
0+
0(
#885
1+
#890
0A
0=
0>
09
b1 H
04
0M
0+
1(
#895
1+
#900
0+
0(
#905
1+
#910
1?
1<
1@
1X
1U
1Y
1;
1T
b0 H
10
0+
1(
#915
0X
0U
0Y
0T
b1 `
1d
1+
#920
0+
0(
#925
1+
#930
0?
0<
0@
0;
b1 H
b1 G
1M
0+
1(
#935
1+
#940
0+
0(
#945
1+
#950
1A
1=
1>
1Z
1V
1W
19
1R
b0 H
00
0+
1(
#955
0Z
0V
0W
0R
15
b11001000 f
0d
1+
#960
0+
0(
#965
1+
#970
0A
0=
0>
09
b1 H
b100000 O
0M
0+
1(
#975
1+
#980
0+
0(
#985
1+
#990
1?
1<
1@
1X
1U
1Y
1;
1T
b0 H
10
0+
1(
#995
0X
0U
0Y
0T
b10 `
1d
1+
#1000
0+
0(
#1005
1+
#1010
0?
0<
0@
0;
b1 H
b10 G
b1 K
1M
0+
1(
#1015
1+
#1020
0+
0(
#1025
1+
#1030
1A
1=
1>
1Z
1V
1W
19
1R
b0 H
00
0+
1(
#1035
0Z
0V
0W
0R
b10010000 f
0d
1+
#1040
0+
0(
#1045
1+
#1050
0A
0=
0>
09
b1 H
b1000000 O
0M
0+
1(
#1055
1+
#1060
0+
0(
#1065
1+
#1070
1?
1<
1@
1X
1U
1Y
1;
1T
b0 H
10
0+
1(
#1075
0X
0U
0Y
0T
b11 `
1d
1+
#1080
0+
0(
#1085
1+
#1090
0?
0<
0@
0;
b1 H
b11 G
b11 K
1M
0+
1(
#1095
1+
#1100
0+
0(
#1105
1+
#1110
1A
1=
1>
1Z
1V
1W
19
1R
b0 H
00
0+
1(
#1115
0Z
0V
0W
0R
05
b100000 f
0d
1+
#1120
0+
0(
#1125
1+
#1130
0A
0=
0>
09
b1 H
14
b10000000 O
0M
0+
1(
#1135
1+
#1140
0+
0(
#1145
1+
#1150
1?
1<
1@
1X
1U
1Y
1;
1T
b0 H
10
0+
1(
#1155
0X
0U
0Y
0T
b100 `
b1 c
1d
1+
#1160
0+
0(
#1165
1+
#1170
0?
0<
0@
0;
b1 H
b100 G
b110 K
1M
0+
1(
#1175
1+
#1180
0+
0(
#1185
1+
#1190
1A
1=
1>
1Z
1V
1W
19
1R
b0 H
00
0+
1(
#1195
0Z
0V
0W
0R
b1000000 f
0d
1+
#1200
0+
0(
#1205
1+
#1210
0A
0=
0>
09
b1 H
04
b0 O
0M
0+
1(
#1215
1+
#1220
0+
0(
#1225
1+
#1230
1?
1<
1@
1X
1U
1Y
1;
1T
b0 H
10
0+
1(
#1235
0X
0U
0Y
0T
b101 `
b10 c
1d
1+
#1240
0+
0(
#1245
1+
#1250
0?
0<
0@
0;
b1 H
b101 G
b1100 K
1M
0+
1(
#1255
1+
#1260
0+
0(
#1265
1+
#1270
1A
1=
1>
1Z
1V
1W
19
1R
b0 H
00
0+
1(
#1275
0Z
0V
0W
0R
15
b10000000 f
0d
1+
#1280
0+
0(
#1285
1+
#1290
0A
0=
0>
09
b1 H
0M
0+
1(
#1295
1+
#1300
0+
0(
#1305
1+
#1310
1?
1<
1@
1X
1U
1Y
1;
1T
b0 H
10
0+
1(
#1315
0X
0U
0Y
0T
b110 `
b100 c
1d
1+
#1320
0+
0(
#1325
1+
#1330
0?
0<
0@
0;
b1 H
b110 G
b11001 K
1M
0+
1(
#1335
1+
#1340
0+
0(
#1345
1+
#1350
1A
1=
1>
1Z
1V
1W
19
1R
b0 H
00
0+
1(
#1355
0Z
0V
0W
0R
05
b0 f
0d
1+
#1360
0+
0(
#1365
1+
#1370
0A
0=
0>
09
b1 H
0M
0+
1(
#1375
1+
#1380
0+
0(
#1385
1+
#1390
1?
1<
1@
1X
1U
1Y
1;
1T
b0 H
10
0+
1(
#1395
0X
0U
0Y
0T
b111 `
b1000 c
1d
1+
#1400
0+
0(
#1405
1+
#1410
0?
0<
0@
0;
b1 H
b111 G
b110010 K
1M
0+
1(
#1415
1+
#1420
0+
0(
#1425
1+
#1430
1A
1=
1>
1Z
1V
1W
19
1R
b0 H
00
0+
1(
#1435
0Z
0V
0W
0R
0d
1+
#1440
0+
0(
#1445
1+
#1450
0A
0=
0>
09
b1 H
0M
0+
1(
#1455
1+
#1460
0+
0(
#1465
1+
#1470
1?
1<
1@
1X
1U
1Y
1;
1T
b0 H
10
0+
1(
#1475
0X
0U
0Y
b11 a
0T
b1000 `
b10000 c
1d
1+
#1480
0+
0(
#1485
b11 e
1+
#1490
0?
0<
0@
b11 I
0;
b1 H
b1000 G
b1100100 K
1M
0+
1(
#1495
z5
b10000 "
b10000 1
b10000 b
b0 `
0#
1!
1+
#1500
0+
0(
#1505
1!
1+
#1510
1A
1=
1>
1Z
1V
1W
b0 I
19
1R
b11 N
b0 H
00
0+
1(
#1515
0Z
0V
0W
0R
1!
0d
1+
#1520
0+
0(
#1525
1!
1+
#1530
0A
0=
0>
b1 I
09
b1 H
b0 N
z4
b1100100 %
b1100100 2
b1100100 J
0&
1$
b0 G
0L
0M
0+
1(
#1535
1!
1+
#1540
0+
0(
#1545
1!
1+
#1550
1?
1<
1@
1X
1U
1Y
b0 a
b10 I
1;
1T
13
0$
b1 N
b0 H
10
0+
1(
#1555
b0 "
b0 1
b0 b
0!
b0 c
0d
b0 e
1+
#1560
0+
0(
#1565
0d
1+
#1570
0?
0<
0@
b1 a
0;
b10 N
1L
1&
b0 K
b100001 O
03
1M
0+
1(
b1000010 ,
b1000010 /
b1000010 S
b100001 )
b100001 .
b100001 :
#1575
0X
0U
0Y
0T
b10 a
1d
b1 e
1+
#1580
0+
0(
#1585
b10 e
1#
b1000010 f
1+
#1590
b1 H
0+
1(
#1595
1+
#1600
0+
0(
#1605
1+
#1610
1A
1=
1>
1Z
1V
1W
19
1R
b0 H
00
0+
1(
#1615
0Z
0V
0W
0R
05
0d
1+
#1620
0+
0(
#1625
1+
#1630
0A
0=
0>
09
04
0M
b1 H
0+
1(
#1635
1+
#1640
0+
0(
#1645
1+
#1650
1?
1<
1@
1X
1U
1Y
1;
1T
b0 H
10
0+
1(
#1655
0X
0U
0Y
0T
b1 `
1d
1+
#1660
0+
0(
#1665
1+
#1670
0?
0<
0@
0;
b1 G
1M
b1 H
0+
1(
#1675
1+
#1680
0+
0(
#1685
1+
#1690
1A
1=
1>
1Z
1V
1W
19
1R
b0 H
00
0+
1(
#1695
0Z
0V
0W
0R
15
b10000100 f
0d
1+
#1700
0+
0(
#1705
1+
#1710
0A
0=
0>
09
b1000010 O
0M
b1 H
0+
1(
#1715
1+
#1720
0+
0(
#1725
1+
