Off_Chip_Protocols/UART_Protocol/UART_Parameterized_BaudRate/8_O_Parity_check.v
module Odd_Par_CHECK(Data,Odd_parity, OpCheck);
  input [7:0] Data;
  input Odd_parity;
  output OpCheck ;
  
  assign OpCheck=~(Odd_parity^Data[7]^Data[6]^Data[5]^Data[4]^Data[3]^Data[2]^Data[1]^Data[0]);
 
endmodule

Off_Chip_Protocols/UART_Protocol/UART_Parameterized_BaudRate/3_UART_Receiver.v
//UART Receiver with 8 Data bit - 1 Stop bit 
`include "8_O_Parity_check.v"


module UART_Receiver(clk,rst,rx_en,Rx,done,dout,frame_err,parity_err);
input clk,rst,rx_en;
output reg [7:0] dout;
input Rx; 
output reg done,frame_err,parity_err;

//Controller
localparam IDLE=3'B000,
           START=3'B001,
           DATA=3'B010,
           PARITY=3'B011,
           STOP=3'B100;

reg [2:0] state,next_state;
reg o_parity;
wire o_parity_check;
reg [7:0] TDR;
reg [3:0] sample;
wire sample_mid,sample_end;
 reg [2:0] index;

assign sample_mid=(sample==4'd8)&&rx_en;
assign sample_end=(sample==4'd15)&&rx_en;
assign sh_en=((rx_en)&&(sample_mid)&&(state==DATA));
 


//parity check
Odd_Par_CHECK pc(.Data(TDR),
	.Odd_parity(o_parity),
	.OpCheck(o_parity_check));
 //sequential logic
always @(posedge clk or posedge rst)begin
        if(rst)
           state<=IDLE;
        else
           state<=next_state;

end
//combinational logic
always @(*)begin
        next_state=state;
        case(state)
		  IDLE: next_state=(Rx==0)? START:IDLE;
          START:begin  if (sample_mid && Rx==1)
                            next_state = IDLE;
                       else
                            next_state=(sample_end)?DATA:START; 
                 end
          DATA: next_state=((sample_end)&&(index==3'd7))? PARITY:DATA;
          PARITY: next_state=(sample_end)? STOP:PARITY;
          STOP:next_state=(sample_end)?IDLE:STOP;
        endcase
end
//output logic upon states
always @(posedge clk or posedge rst)begin	
    if (rst)begin 
	    sample<=0;
        frame_err<=0;
	    parity_err<=0;
	    done<=0;
        index<=0;
    	dout<=0;
	    o_parity<=0;
	 
    end
    else begin
      done<=0;
       if (state != next_state)
           sample <= 0;
       else if(rx_en && (state==START || state==DATA || state==PARITY || state==STOP))begin
           if(sample == 4'd15)
              sample <= 4'd0;
           else
              sample <= sample + 1'b1;
      end

    end
        case(state)
		IDLE:begin
            TDR<=0;  
            index<=0;
            sample <= 0;
			frame_err<=0;
	        parity_err<=0;
		    done<=0;
                end
			
          START:begin
                frame_err <= 0;
                parity_err <= 0; 
                index<=0;
                end
			
         DATA:begin
           if(sample_mid)
             TDR[index]<=Rx;
           if(sample_end)
               index<=index+1;    
         end
			
		PARITY:begin
			if(sample_mid)	
               o_parity<=Rx;  
		end
			
        STOP:begin
          if(sample_mid)begin 
		        frame_err<=~Rx;
                parity_err<=o_parity_check;
                dout<=TDR;
		      end
          if(sample_end)
             done<=1;
		end
			
        endcase
    end
endmodule

Off_Chip_Protocols/UART_Protocol/UART_Parameterized_BaudRate/7_Parity_Gen.v
module parity_gen (
    input clk,
    input rst,
    input load,
    input [7:0] x,
    output reg odd
);
always @(posedge clk or posedge rst) begin
    if (rst)
        odd<=0;
    else if (load)      //TX FSM asserts load
      odd<=~(^x);      // XNOR all bits → odd parity
end
endmodule

Off_Chip_Protocols/UART_Protocol/UART_Parameterized_BaudRate/6_PISO.v
//Right  shift
module PISO (input [7:0] Data_in,input load, clk,rst,tx_en,output reg Q );
  reg [7:0]Q_temp;
  always @(posedge clk or posedge rst)begin
    if(rst)begin
      Q_temp<={8{1'B0}};
      Q<=0;
    end                // here LSB is  Q[0] and MSB is Q[3]
    else if (load)
     Q_temp<=Data_in;
    else if(tx_en) begin
      Q<=Q_temp[0];
      Q_temp<={1'B0,Q_temp[7:1]};
 
    end

  end
endmodule

Off_Chip_Protocols/UART_Protocol/UART_Parameterized_BaudRate/2_UART_Transmitter.v
`include "7_Parity_Gen.v"
`include "6_PISO.v"

module UART_Transmitter (clk,rst,tx_en,w_en,TDR,Tx,busy);
input clk,rst,tx_en,w_en;
input [7:0] TDR;
output reg Tx;
output reg busy;

//Controller

localparam IDLE=3'B000,
        	START=3'B001,
	        DATA=3'B010,
	        PARITY=3'B011,
	        STOP=3'B100;


reg [2:0] state,next_state;
reg [2:0] counter;
wire load;
wire TSR;
wire parity;

//shift register for converting the parallel input into serial stream of data
//to be sent
 PISO piso(.Data_in(TDR),
	 .load(load),
	 .clk(clk),
	 .rst(rst),
	 .Q(TSR),
	 .tx_en(tx_en));
 

 //Parity generator
 parity_gen  par(.clk(clk),
	 .rst(rst),
	 .x(TDR),
	 .load(load),
	 .odd(parity));
 //sequential logic
always @(posedge clk or posedge rst)begin
	if(rst)
           state<=IDLE;
           
	else
		state<=next_state;

end
//combinational logic
always @(*)begin
	next_state=state;
	case(state)
		IDLE: next_state=(w_en)? START:IDLE;
		START: next_state=(tx_en)? DATA:START;
		DATA: next_state=((tx_en==1)&&(counter==3'd7))? PARITY:DATA;
		PARITY: next_state=(tx_en)? STOP:PARITY;
		STOP:next_state=(tx_en)? IDLE:STOP;
	endcase

end
//output logic upon states

assign load =(( state==IDLE)&&( next_state==START));
always @(posedge clk or posedge rst)begin
    if (rst)begin
            Tx<=1;
	    busy<=0;
	    counter<=0;
    end
    else begin
	case(state)
		IDLE:begin
			Tx<=1;
			busy<=0;
			counter<=0;
		end
		START:begin
			Tx<=0;
			busy<=1;
			counter<=0;
		end
		DATA:begin
			Tx<=TSR;
			busy<=1;
                        if(tx_en)
				counter<=counter+1;
		end
		PARITY:begin
			Tx<=parity;
			busy<=1;
			counter<=0;
		end
		STOP:begin
			Tx<=1;
			busy<=1;
			counter<=0;
		end
	endcase
    end
    end
    endmodule

Off_Chip_Protocols/UART_Protocol/UART_Parameterized_BaudRate/5_Receiver_Baud_Gen.v
module receiver_baud_gen #(parameter baudrate=115200,r_frq=100000000)(clk,rst,rx_en);
input clk,rst;
output reg rx_en;

  reg [$clog2(r_frq/baudrate):0] count;

always @(posedge clk or posedge rst)begin

        if(rst)begin
                rx_en<=0;
                count<=0;
        end

  else if(count==(r_frq/baudrate)/16)begin  //count 
                rx_en<=1;
                count<=0;
        end
        else begin
                count<=count+1;
                rx_en<=0;
        end

        end
endmodule

Off_Chip_Protocols/UART_Protocol/UART_Parameterized_BaudRate/4_Transmitter_Baud_Gen.v

module transmitter_baud_gen #(parameter baudrate=115200,t_frq=50000000)(clk,rst,tx_en);
input clk,rst;
output reg tx_en;

reg [$clog2(t_frq/baudrate):0]count;

always @(posedge clk or posedge rst)begin

	if(rst)begin
		tx_en<=0;
		count<=0;
	end

  else if(count==t_frq/baudrate)begin  //count
		tx_en<=1;
	        count<=0;
	end
	else begin
		count<=count+1;
	        tx_en<=0;
	end

        end 
endmodule

Off_Chip_Protocols/UART_Protocol/UART_Parameterized_BaudRate/1_Top.v
`include "2_UART_Transmitter.v"
`include "3_UART_Receiver.v"
`include "4_Transmitter_Baud_Gen.v"
`include "5_Receiver_Baud_Gen.v"

module top #(parameter baudrate=115200,t_frq=50000000,r_frq=100000000) (
input t_clk,r_clk,rst,w_en,
input [7:0] TDR,
output busy,done,frame_err,parity_err,
output [7:0] dout);


wire tx_en,rx_en; //from baud generators to transmitter and receiver
wire Tx;    //serial output from Transmitter to the Receiver
  
reg rx_sync1,rx_sync2;

always @(posedge r_clk or posedge rst) begin
  if(rst)begin
    rx_sync1<=1'b1;
    rx_sync2<=1'b1;
  end else begin
    rx_sync1<=Tx;
    rx_sync2<=rx_sync1;
  end
end
  
  transmitter_baud_gen #(.baudrate(baudrate),.t_frq(t_frq))
                     tbg(.clk(t_clk),
                         .rst(rst),
                         .tx_en(tx_en));
                         
  receiver_baud_gen #(.baudrate(baudrate),.r_frq(r_frq))
                  rbg(.clk(r_clk),
                      .rst(rst),
                      .rx_en(rx_en));
                      
UART_Transmitter  transmit(.clk(t_clk),
                 .rst(rst),
                 .tx_en(tx_en),
                 .w_en(w_en),
                 .TDR(TDR),
                 .Tx(Tx),
                 .busy(busy));
                 
UART_Receiver receive(.clk(r_clk),
              .rst(rst),
              .rx_en(rx_en),
              .Rx(rx_sync2),
              .done(done),
              .dout(dout),
              .frame_err(frame_err),
              .parity_err(parity_err));
              
              
endmodule

Off_Chip_Protocols/UART_Protocol/UART_Parameterized_BaudRate/9_TestBench.v

module uart_tb #(parameter baudrate=115200,t_frq=50000000,r_frq=100000000);

reg t_clk;
reg r_clk;
reg rst;
reg w_en;
reg [7:0]TDR;

wire busy;
wire done;
wire frame_err;
wire parity_err;
wire [7:0] dout;


  top #(.baudrate(baudrate),.t_frq(t_frq),.r_frq(r_frq)) DUT (.t_clk(t_clk),
    .r_clk(r_clk),
    .rst(rst),
    .w_en(w_en),
    .TDR(TDR),
    .busy(busy),
    .done(done),
    .frame_err(frame_err),
    .parity_err(parity_err),
    .dout(dout)
);


always #20 t_clk=~t_clk;   // 50MHz


always #10 r_clk=~r_clk;   //100MHZ

initial begin
    t_clk=0;
    r_clk= 0;
    rst=1;
    w_en=0;
    TDR=8'd0;

    #200;
    rst=0;

   TDR=8'd20;
  repeat(10) begin@(posedge t_clk);

   
     TDR=TDR+20;
    w_en=1;
    @(posedge t_clk);
    w_en=0;
 

    // wait for Receiver to be done
    wait(done==1);

  $display("************************************");
    $display("Sent= %d",TDR);
    $display("Received=%d",dout);
    $display("FrameErr=%b",frame_err);
    $display("ParityErr=%b",parity_err);
  $display("************************************");
end
    #2000;
    $finish;
end

initial begin
    $dumpfile("uart.vcd");
    $dumpvars(0, uart_tb);

$monitor("t=%0t  busy=%b done=%b frame_err=%b parity_err=%b dout=%d",$time,busy,done,frame_err,parity_err,dout);
end

endmodule

Off_Chip_Protocols/UART_Protocol/UART_Parameterized_BaudRate/uart.vcd
$date
	Thu Mar  5 06:43:10 2026
$end
$version
	Icarus Verilog
$end
$timescale
	1s
$end
$scope module uart_tb $end
$var wire 1 ! parity_err $end
$var wire 1 " frame_err $end
$var wire 8 # dout [7:0] $end
$var wire 1 $ done $end
$var wire 1 % busy $end
$var parameter 32 & baudrate $end
$var parameter 32 ' r_frq $end
$var parameter 32 ( t_frq $end
$var reg 8 ) TDR [7:0] $end
$var reg 1 * r_clk $end
$var reg 1 + rst $end
$var reg 1 , t_clk $end
$var reg 1 - w_en $end
$scope module DUT $end
$var wire 8 . TDR [7:0] $end
$var wire 1 * r_clk $end
$var wire 1 + rst $end
$var wire 1 , t_clk $end
$var wire 1 - w_en $end
$var wire 1 / tx_en $end
$var wire 1 0 rx_en $end
$var wire 1 ! parity_err $end
$var wire 1 " frame_err $end
$var wire 8 1 dout [7:0] $end
$var wire 1 $ done $end
$var wire 1 % busy $end
$var wire 1 2 Tx $end
$var parameter 32 3 baudrate $end
$var parameter 32 4 r_frq $end
$var parameter 32 5 t_frq $end
$var reg 1 6 rx_sync1 $end
$var reg 1 7 rx_sync2 $end
$scope module rbg $end
$var wire 1 * clk $end
$var wire 1 + rst $end
$var parameter 32 8 baudrate $end
$var parameter 32 9 r_frq $end
$var reg 11 : count [10:0] $end
$var reg 1 0 rx_en $end
$upscope $end
$scope module receive $end
$var wire 1 7 Rx $end
$var wire 1 * clk $end
$var wire 1 + rst $end
$var wire 1 0 rx_en $end
$var wire 1 ; sample_end $end
$var wire 1 < sample_mid $end
$var wire 1 = sh_en $end
$var wire 1 > o_parity_check $end
$var parameter 3 ? DATA $end
$var parameter 3 @ IDLE $end
$var parameter 3 A PARITY $end
$var parameter 3 B START $end
$var parameter 3 C STOP $end
$var reg 8 D TDR [7:0] $end
$var reg 1 $ done $end
$var reg 8 E dout [7:0] $end
$var reg 1 " frame_err $end
$var reg 3 F index [2:0] $end
$var reg 3 G next_state [2:0] $end
$var reg 1 H o_parity $end
$var reg 1 ! parity_err $end
$var reg 4 I sample [3:0] $end
$var reg 3 J state [2:0] $end
$scope module pc $end
$var wire 8 K Data [7:0] $end
$var wire 1 H Odd_parity $end
$var wire 1 > OpCheck $end
$upscope $end
$upscope $end
$scope module tbg $end
$var wire 1 , clk $end
$var wire 1 + rst $end
$var parameter 32 L baudrate $end
$var parameter 32 M t_frq $end
$var reg 10 N count [9:0] $end
$var reg 1 / tx_en $end
$upscope $end
$scope module transmit $end
$var wire 8 O TDR [7:0] $end
$var wire 1 , clk $end
$var wire 1 P load $end
$var wire 1 + rst $end
$var wire 1 / tx_en $end
$var wire 1 - w_en $end
$var wire 1 Q parity $end
$var wire 1 R TSR $end
$var parameter 3 S DATA $end
$var parameter 3 T IDLE $end
$var parameter 3 U PARITY $end
$var parameter 3 V START $end
$var parameter 3 W STOP $end
$var reg 1 2 Tx $end
$var reg 1 % busy $end
$var reg 3 X counter [2:0] $end
$var reg 3 Y next_state [2:0] $end
$var reg 3 Z state [2:0] $end
$scope module par $end
$var wire 1 , clk $end
$var wire 1 P load $end
$var wire 1 + rst $end
$var wire 8 [ x [7:0] $end
$var reg 1 Q odd $end
$upscope $end
$scope module piso $end
$var wire 8 \ Data_in [7:0] $end
$var wire 1 , clk $end
$var wire 1 P load $end
$var wire 1 + rst $end
$var wire 1 / tx_en $end
$var reg 1 R Q $end
$var reg 8 ] Q_temp [7:0] $end
$upscope $end
$upscope $end
$upscope $end
$upscope $end
$enddefinitions $end
$comment Show the parameter values. $end
$dumpall
b100 W
b1 V
b11 U
b0 T
b10 S
b10111110101111000010000000 M
b11100001000000000 L
b100 C
b1 B
b11 A
b0 @
b10 ?
b101111101011110000100000000 9
b11100001000000000 8
b10111110101111000010000000 5
b101111101011110000100000000 4
b11100001000000000 3
b10111110101111000010000000 (
b101111101011110000100000000 '
b11100001000000000 &
$end
#0
$dumpvars
b0 ]
b0 \
b0 [
b0 Z
b0 Y
b0 X
0R
0Q
0P
b0 O
b0 N
bx K
b0 J
b0 I
0H
b0 G
b0 F
b0 E
bx D
x>
0=
0<
0;
b0 :
17
16
12
b0 1
00
0/
b0 .
0-
0,
1+
0*
b0 )
0%
0$
b0 #
0"
0!
$end
#5
1>
b0 D
b0 K
1*
#10
0*
1,
#15
1*
#20
0*
0,
#25
1*
#30
0*
1,
#35
1*
#40
0*
0,
#45
1*
#50
0*
1,
#55
1*
#60
0*
0,
#65
1*
#70
0*
1,
#75
1*
#80
0*
0,
#85
1*
#90
0*
1,
#95
1*
#100
0*
0,
#105
1*
#110
0*
1,
#115
1*
#120
0*
0,
#125
1*
#130
0*
1,
#135
1*
#140
0*
0,
#145
1*
#150
0*
1,
#155
1*
#160
0*
0,
#165
1*
#170
0*
1,
#175
1*
#180
0*
0,
#185
1*
#190
0*
1,
#195
1*
#200
0*
0,
b10100 )
b10100 .
b10100 O
b10100 [
b10100 \
0+
#205
b1 :
1*
#210
b1 N
1P
b1 Y
1-
b101000 )
b101000 .
b101000 O
b101000 [
b101000 \
0*
1,
#215
b10 :
1*
#220
0*
0,
#225
b11 :
1*
#230
b10 N
b101000 ]
1Q
b1 Z
0P
b1 Y
0-
0*
1,
#235
b100 :
1*
#240
0*
0,
#245
b101 :
1*
#250
1%
02
b11 N
0*
1,
#255
b110 :
06
1*
#260
0*
0,
#265
b1 G
07
b111 :
1*
#270
b100 N
0*
1,
#275
b1000 :
b1 J
1*
#280
0*
0,
#285
b1001 :
1*
#290
b101 N
0*
1,
#295
b1010 :
1*
#300
0*
0,
#305
b1011 :
1*
#310
b110 N
0*
1,
#315
b1100 :
1*
#320
0*
0,
#325
b1101 :
1*
#330
b111 N
0*
1,
#335
b1110 :
1*
#340
0*
0,
#345
b1111 :
1*
#350
b1000 N
0*
1,
#355
b10000 :
1*
#360
0*
0,
#365
b10001 :
1*
#370
b1001 N
0*
1,
#375
b10010 :
1*
#380
0*
0,
#385
b10011 :
1*
#390
b1010 N
0*
1,
#395
b10100 :
1*
#400
0*
0,
#405
b10101 :
1*
#410
b1011 N
0*
1,
#415
b10110 :
1*
#420
0*
0,
#425
b10111 :
1*
#430
b1100 N
0*
1,
#435
b11000 :
1*
#440
0*
0,
#445
b11001 :
1*
#450
b1101 N
0*
1,
#455
b11010 :
1*
#460
0*
0,
#465
b11011 :
1*
#470
b1110 N
0*
1,
#475
b11100 :
1*
#480
0*
0,
#485
b11101 :
1*
#490
b1111 N
0*
1,
#495
b11110 :
1*
#500
0*
0,
#505
b11111 :
1*
#510
b10000 N
0*
1,
#515
b100000 :
1*
#520
0*
0,
#525
b100001 :
1*
#530
b10001 N
0*
1,
#535
b100010 :
1*
#540
0*
0,
#545
b100011 :
1*
#550
b10010 N
0*
1,
#555
b100100 :
1*
#560
0*
0,
#565
b100101 :
1*
#570
b10011 N
0*
1,
#575
b100110 :
1*
#580
0*
0,
#585
b100111 :
1*
#590
b10100 N
0*
1,
#595
b101000 :
1*
#600
0*
0,
#605
b101001 :
1*
#610
b10101 N
0*
1,
#615
b101010 :
1*
#620
0*
0,
#625
b101011 :
1*
#630
b10110 N
0*
1,
#635
b101100 :
1*
#640
0*
0,
#645
b101101 :
1*
#650
b10111 N
0*
1,
#655
b101110 :
1*
#660
0*
0,
#665
b101111 :
1*
#670
b11000 N
0*
1,
#675
b110000 :
1*
#680
0*
0,
#685
b110001 :
1*
#690
b11001 N
0*
1,
#695
b110010 :
1*
#700
0*
0,
#705
b110011 :
1*
#710
b11010 N
0*
1,
#715
b110100 :
1*
#720
0*
0,
#725
b110101 :
1*
#730
b11011 N
0*
1,
#735
b110110 :
1*
#740
0*
0,
#745
b0 :
10
1*
#750
b11100 N
0*
1,
#755
00
b1 :
b1 I
1*
#760
0*
0,
#765
b10 :
1*
#770
b11101 N
0*
1,
#775
b11 :
1*
#780
0*
0,
#785
b100 :
1*
#790
b11110 N
0*
1,
#795
b101 :
1*
#800
0*
0,
#805
b110 :
1*
#810
b11111 N
0*
1,
#815
b111 :
1*
#820
0*
0,
#825
b1000 :
1*
#830
b100000 N
0*
1,
#835
b1001 :
1*
#840
0*
0,
#845
b1010 :
1*
#850
b100001 N
0*
1,
#855
b1011 :
1*
#860
0*
0,
#865
b1100 :
1*
#870
b100010 N
0*
1,
#875
b1101 :
1*
#880
0*
0,
#885
b1110 :
1*
#890
b100011 N
0*
1,
#895
b1111 :
1*
#900
0*
0,
#905
b10000 :
1*
#910
b100100 N
0*
1,
#915
b10001 :
1*
#920
0*
0,
#925
b10010 :
1*
#930
b100101 N
0*
1,
#935
b10011 :
1*
#940
0*
0,
#945
b10100 :
1*
#950
b100110 N
0*
1,
#955
b10101 :
1*
#960
0*
0,
#965
b10110 :
1*
#970
b100111 N
0*
1,
#975
b10111 :
1*
#980
0*
0,
#985
b11000 :
1*
#990
b101000 N
0*
1,
#995
b11001 :
1*
#1000
0*
0,
#1005
b11010 :
1*
#1010
b101001 N
0*
1,
#1015
b11011 :
1*
#1020
0*
0,
#1025
b11100 :
1*
#1030
b101010 N
0*
1,
#1035
b11101 :
1*
#1040
0*
0,
#1045
b11110 :
1*
#1050
b101011 N
0*
1,
#1055
b11111 :
1*
#1060
0*
0,
#1065
b100000 :
1*
#1070
b101100 N
0*
1,
#1075
b100001 :
1*
#1080
0*
0,
#1085
b100010 :
1*
#1090
b101101 N
0*
1,
#1095
b100011 :
1*
#1100
0*
0,
#1105
b100100 :
1*
#1110
b101110 N
0*
1,
#1115
b100101 :
1*
#1120
0*
0,
#1125
b100110 :
1*
#1130
b101111 N
0*
1,
#1135
b100111 :
1*
#1140
0*
0,
#1145
b101000 :
1*
#1150
b110000 N
0*
1,
#1155
b101001 :
1*
#1160
0*
0,
#1165
b101010 :
1*
#1170
b110001 N
0*
1,
#1175
b101011 :
1*
#1180
0*
0,
#1185
b101100 :
1*
#1190
b110010 N
0*
1,
#1195
b101101 :
1*
#1200
0*
0,
#1205
b101110 :
1*
#1210
b110011 N
0*
1,
#1215
b101111 :
1*
#1220
0*
0,
#1225
b110000 :
1*
#1230
b110100 N
0*
1,
#1235
b110001 :
1*
#1240
0*
0,
#1245
b110010 :
1*
#1250
b110101 N
0*
1,
#1255
b110011 :
1*
#1260
0*
0,
#1265
b110100 :
1*
#1270
b110110 N
0*
1,
#1275
b110101 :
1*
#1280
0*
0,
#1285
b110110 :
1*
#1290
b110111 N
0*
1,
#1295
b0 :
10
1*
#1300
0*
0,
#1305
b10 I
00
b1 :
1*
#1310
b111000 N
0*
1,
#1315
b10 :
1*
#1320
0*
0,
#1325
b11 :
1*
#1330
b111001 N
0*
1,
#1335
b100 :
1*
#1340
0*
0,
#1345
b101 :
1*
#1350
b111010 N
0*
1,
#1355
b110 :
1*
#1360
0*
0,
#1365
b111 :
1*
#1370
b111011 N
0*
1,
#1375
b1000 :
1*
#1380
0*
0,
#1385
b1001 :
1*
#1390
b111100 N
0*
1,
#1395
b1010 :
1*
#1400
0*
0,
#1405
b1011 :
1*
#1410
b111101 N
0*
1,
#1415
b1100 :
1*
#1420
0*
0,
#1425
b1101 :
1*
#1430
b111110 N
0*
1,
#1435
b1110 :
1*
#1440
0*
0,
#1445
b1111 :
1*
#1450
b111111 N
0*
1,
#1455
b10000 :
1*
#1460
0*
0,
#1465
b10001 :
1*
#1470
b1000000 N
0*
1,
#1475
b10010 :
1*
#1480
0*
0,
#1485
b10011 :
1*
#1490
b1000001 N
0*
1,
#1495
b10100 :
1*
#1500
0*
0,
#1505
b10101 :
1*
#1510
b1000010 N
0*
1,
#1515
b10110 :
1*
#1520
0*
0,
#1525
b10111 :
1*
#1530
b1000011 N
0*
1,
#1535
b11000 :
1*
#1540
0*
0,
#1545
b11001 :
1*
#1550
b1000100 N
0*
1,
#1555
b11010 :
1*
#1560
0*
0,
#1565
b11011 :
1*
#1570
b1000101 N
0*
1,
#1575
b11100 :
1*
#1580
0*
0,
#1585
b11101 :
1*
#1590
b1000110 N
0*
1,
#1595
b11110 :
1*
#1600
0*
0,
#1605
b11111 :
1*
#1610
b1000111 N
0*
1,
#1615
b100000 :
1*
#1620
0*
0,
#1625
b100001 :
1*
#1630
b1001000 N
0*
1,
#1635
b100010 :
1*
#1640
0*
0,
#1645
b100011 :
1*
#1650
b1001001 N
0*
1,
#1655
b100100 :
1*
#1660
0*
0,
#1665
b100101 :
1*
#1670
b1001010 N
0*
1,
#1675
b100110 :
1*
#1680
0*
0,
#1685
b100111 :
1*
#1690
b1001011 N
0*
1,
#1695
b101000 :
1*
#1700
0*
0,
#1705
b101001 :
1*
#1710
b1001100 N
0*
1,
#1715
b101010 :
1*
#1720
0*
0,
#1725
b101011 :
1*
#1730
b1001101 N
0*
1,
#1735
b101100 :
1*
#1740
0*
0,
#1745
b101101 :
1*
#1750
b1001110 N
0*
1,
#1755
b101110 :
1*
#1760
0*
0,
#1765
b101111 :
1*
#1770
b1001111 N
0*
1,
#1775
b110000 :
1*
#1780
0*
0,
#1785
b110001 :
1*
#1790
b1010000 N
0*
1,
#1795
b110010 :
1*
#1800
0*
0,
#1805
b110011 :
1*
#1810
b1010001 N
0*
1,
#1815
b110100 :
1*
#1820
0*
0,
#1825
b110101 :
1*
#1830
b1010010 N
0*
1,
#1835
b110110 :
1*
#1840
0*
0,
#1845
b0 :
10
1*
#1850
b1010011 N
0*
1,
#1855
00
b1 :
b11 I
1*
#1860
0*
0,
#1865
b10 :
1*
#1870
b1010100 N
0*
1,
#1875
b11 :
1*
#1880
0*
0,
#1885
b100 :
1*
#1890
b1010101 N
0*
1,
#1895
b101 :
1*
#1900
0*
0,
#1905
b110 :
1*
#1910
b1010110 N
0*
1,
#1915
b111 :
1*
#1920
0*
0,
#1925
b1000 :
1*
#1930
b1010111 N
0*
1,
#1935
b1001 :
1*
#1940
0*
0,
#1945
b1010 :
1*
#1950
b1011000 N
0*
1,
#1955
b1011 :
1*
#1960
0*
0,
#1965
b1100 :
1*
#1970
b1011001 N
0*
1,
#1975
b1101 :
1*
#1980
0*
0,
#1985
b1110 :
1*
#1990
b1011010 N
0*
1,
#1995
b1111 :
1*
#2000
0*
0,
#2005
b10000 :
1*
#2010
b1011011 N
0*
1,
#2015
b10001 :
1*
#2020
0*
0,
#2025
b10010 :
1*
#2030
b1011100 N
0*
1,
#2035
b10011 :
1*
#2040
0*
0,
#2045
b10100 :
1*
#2050
b1011101 N
0*
1,
#2055
b10101 :
1*
#2060
0*
0,
#2065
b10110 :
1*
#2070
b1011110 N
0*
1,
#2075
b10111 :
1*
#2080
0*
0,
#2085
b11000 :
1*
#2090
b1011111 N
0*
1,
#2095
b11001 :
1*
#2100
0*
0,
#2105
b11010 :
1*
#2110
b1100000 N
0*
1,
#2115
b11011 :
1*
#2120
0*
0,
#2125
b11100 :
1*
#2130
b1100001 N
0*
1,
#2135
b11101 :
1*
#2140
0*
0,
#2145
b11110 :
1*
#2150
b1100010 N
0*
1,
#2155
b11111 :
1*
#2160
0*
0,
#2165
b100000 :
1*
#2170
b1100011 N
0*
1,
#2175
b100001 :
1*
#2180
0*
0,
#2185
b100010 :
1*
#2190
b1100100 N
0*
1,
#2195
b100011 :
1*
#2200
0*
0,
#2205
b100100 :
1*
#2210
b1100101 N
0*
1,
#2215
b100101 :
1*
#2220
0*
0,
#2225
b100110 :
1*
#2230
b1100110 N
0*
1,
#2235
b100111 :
1*
#2240
0*
0,
#2245
b101000 :
1*
#2250
b1100111 N
0*
1,
#2255
b101001 :
1*
#2260
0*
0,
#2265
b101010 :
1*
#2270
b1101000 N
0*
1,
#2275
b101011 :
1*
#2280
0*
0,
#2285
b101100 :
1*
#2290
b1101001 N
0*
1,
#2295
b101101 :
1*
#2300
0*
0,
#2305
b101110 :
1*
#2310
b1101010 N
0*
1,
#2315
b101111 :
1*
#2320
0*
0,
#2325
b110000 :
1*
#2330
b1101011 N
0*
1,
#2335
b110001 :
1*
#2340
0*
0,
#2345
b110010 :
1*
#2350
b1101100 N
0*
1,
#2355
b110011 :
1*
#2360
0*
0,
#2365
b110100 :
1*
#2370
b1101101 N
0*
1,
#2375
b110101 :
1*
#2380
0*
0,
#2385
b110110 :
1*
#2390
b1101110 N
0*
1,
#2395
b0 :
10
1*
#2400
0*
0,
#2405
b100 I
00
b1 :
1*
#2410
b1101111 N
0*
1,
#2415
b10 :
1*
#2420
0*
0,
#2425
b11 :
1*
#2430
b1110000 N
0*
1,
#2435
b100 :
1*
#2440
0*
0,
#2445
b101 :
1*
#2450
b1110001 N
0*
1,
#2455
b110 :
1*
#2460
0*
0,
#2465
b111 :
1*
#2470
b1110010 N
0*
1,
#2475
b1000 :
1*
#2480
0*
0,
#2485
b1001 :
1*
#2490
b1110011 N
0*
1,
#2495
b1010 :
1*
#2500
0*
0,
#2505
b1011 :
1*
#2510
b1110100 N
0*
1,
#2515
b1100 :
1*
#2520
0*
0,
#2525
b1101 :
1*
#2530
b1110101 N
0*
1,
#2535
b1110 :
1*
#2540
0*
0,
#2545
b1111 :
1*
#2550
b1110110 N
0*
1,
#2555
b10000 :
1*
#2560
0*
0,
#2565
b10001 :
1*
#2570
b1110111 N
0*
1,
#2575
b10010 :
1*
#2580
0*
0,
#2585
b10011 :
1*
#2590
b1111000 N
0*
1,
#2595
b10100 :
1*
#2600
0*
0,
#2605
b10101 :
1*
#2610
b1111001 N
0*
1,
#2615
b10110 :
1*
#2620
0*
0,
#2625
b10111 :
1*
#2630
b1111010 N
0*
1,
#2635
b11000 :
1*
#2640
0*
0,
#2645
b11001 :
1*
#2650
b1111011 N
0*
1,
#2655
b11010 :
1*
#2660
0*
0,
#2665
b11011 :
1*
#2670
b1111100 N
0*
1,
#2675
b11100 :
1*
#2680
0*
0,
#2685
b11101 :
1*
#2690
b1111101 N
0*
1,
#2695
b11110 :
1*
#2700
0*
0,
#2705
b11111 :
1*
#2710
b1111110 N
0*
1,
#2715
b100000 :
1*
#2720
0*
0,
#2725
b100001 :
1*
#2730
b1111111 N
0*
1,
#2735
b100010 :
1*
#2740
0*
0,
#2745
b100011 :
1*
#2750
b10000000 N
0*
1,
#2755
b100100 :
1*
#2760
0*
0,
#2765
b100101 :
1*
#2770
b10000001 N
0*
1,
#2775
b100110 :
1*
#2780
0*
0,
#2785
b100111 :
1*
#2790
b10000010 N
0*
1,
#2795
b101000 :
1*
#2800
0*
0,
#2805
b101001 :
1*
#2810
b10000011 N
0*
1,
#2815
b101010 :
1*
#2820
0*
0,
#2825
b101011 :
1*
#2830
b10000100 N
0*
1,
#2835
b101100 :
1*
#2840
0*
0,
#2845
b101101 :
1*
#2850
b10000101 N
0*
1,
#2855
b101110 :
1*
#2860
0*
0,
#2865
b101111 :
1*
#2870
b10000110 N
0*
1,
#2875
b110000 :
1*
#2880
0*
0,
#2885
b110001 :
1*
#2890
b10000111 N
0*
1,
#2895
b110010 :
1*
#2900
0*
0,
#2905
b110011 :
1*
#2910
b10001000 N
0*
1,
#2915
b110100 :
1*
#2920
0*
0,
#2925
b110101 :
1*
#2930
b10001001 N
0*
1,
#2935
b110110 :
1*
#2940
0*
0,
#2945
b0 :
10
1*
#2950
b10001010 N
0*
1,
#2955
00
b1 :
b101 I
1*
#2960
0*
0,
#2965
b10 :
1*
#2970
b10001011 N
0*
1,
#2975
b11 :
1*
#2980
0*
0,
#2985
b100 :
1*
#2990
b10001100 N
0*
1,
#2995
b101 :
1*
#3000
0*
0,
#3005
b110 :
1*
#3010
b10001101 N
0*
1,
#3015
b111 :
1*
#3020
0*
0,
#3025
b1000 :
1*
#3030
b10001110 N
0*
1,
#3035
b1001 :
1*
#3040
0*
0,
#3045
b1010 :
1*
#3050
b10001111 N
0*
1,
#3055
b1011 :
1*
#3060
0*
0,
#3065
b1100 :
1*
#3070
b10010000 N
0*
1,
#3075
b1101 :
1*
#3080
0*
0,
#3085
b1110 :
1*
#3090
b10010001 N
0*
1,
#3095
b1111 :
1*
#3100
0*
0,
#3105
b10000 :
1*
#3110
b10010010 N
0*
1,
#3115
b10001 :
1*
#3120
0*
0,
#3125
b10010 :
1*
#3130
b10010011 N
0*
1,
