Off_Chip_Protocols/UART_Protocol/UART_Parameterized_BaudRate/8_O_Parity_check.v
module Odd_Par_CHECK(Data,Odd_parity, OpCheck);
  input [7:0] Data;
  input Odd_parity;
  output OpCheck ;
  
  assign OpCheck=~(Odd_parity^Data[7]^Data[6]^Data[5]^Data[4]^Data[3]^Data[2]^Data[1]^Data[0]);
 
endmodule

Off_Chip_Protocols/UART_Protocol/UART_Parameterized_BaudRate/3_UART_Receiver.v
//UART Receiver with 8 Data bit - 1 Stop bit 
`include "8_O_Parity_check.v"


module UART_Receiver(clk,rst,rx_en,Rx,done,dout,frame_err,parity_err);
input clk,rst,rx_en;
output reg [7:0] dout;
input Rx; 
output reg done,frame_err,parity_err;

//Controller
localparam IDLE=3'B000,
           START=3'B001,
           DATA=3'B010,
           PARITY=3'B011,
           STOP=3'B100;

reg [2:0] state,next_state;
reg o_parity;
wire o_parity_check;
reg [7:0] TDR;
reg [3:0] sample;
wire sample_mid,sample_end;
 reg [2:0] index;

assign sample_mid=(sample==4'd8)&&rx_en;
assign sample_end=(sample==4'd15)&&rx_en;
assign sh_en=((rx_en)&&(sample_mid)&&(state==DATA));
 


//parity check
Odd_Par_CHECK pc(.Data(TDR),
	.Odd_parity(o_parity),
	.OpCheck(o_parity_check));
 //sequential logic
always @(posedge clk or posedge rst)begin
        if(rst)
           state<=IDLE;
        else
           state<=next_state;

end
//combinational logic
always @(*)begin
        next_state=state;
        case(state)
		  IDLE: next_state=(Rx==0)? START:IDLE;
          START:begin  if (sample_mid && Rx==1)
                            next_state = IDLE;
                       else
                            next_state=(sample_end)?DATA:START; 
                 end
          DATA: next_state=((sample_end)&&(index==3'd7))? PARITY:DATA;
          PARITY: next_state=(sample_end)? STOP:PARITY;
          STOP:next_state=(sample_end)?IDLE:STOP;
        endcase
end
//output logic upon states
always @(posedge clk or posedge rst)begin	
    if (rst)begin 
	    sample<=0;
        frame_err<=0;
	    parity_err<=0;
	    done<=0;
        index<=0;
    	dout<=0;
	    o_parity<=0;
	 
    end
    else begin
      done<=0;
       if (state != next_state)
           sample <= 0;
       else if(rx_en && (state==START || state==DATA || state==PARITY || state==STOP))begin
           if(sample == 4'd15)
              sample <= 4'd0;
           else
              sample <= sample + 1'b1;
      end

    end
        case(state)
		IDLE:begin
            TDR<=0;  
            index<=0;
            sample <= 0;
			frame_err<=0;
	        parity_err<=0;
		    done<=0;
                end
			
          START:begin
                frame_err <= 0;
                parity_err <= 0; 
                index<=0;
                end
			
         DATA:begin
           if(sample_mid)
             TDR[index]<=Rx;
           if(sample_end)
               index<=index+1;    
         end
			
		PARITY:begin
			if(sample_mid)	
               o_parity<=Rx;  
		end
			
        STOP:begin
          if(sample_mid)begin 
		        frame_err<=~Rx;
                parity_err<=o_parity_check;
                dout<=TDR;
		      end
          if(sample_end)
             done<=1;
		end
			
        endcase
    end
endmodule

Off_Chip_Protocols/UART_Protocol/UART_Parameterized_BaudRate/7_Parity_Gen.v
module parity_gen (
    input clk,
    input rst,
    input load,
    input [7:0] x,
    output reg odd
);
always @(posedge clk or posedge rst) begin
    if (rst)
        odd<=0;
    else if (load)      //TX FSM asserts load
      odd<=~(^x);      // XNOR all bits → odd parity
end
endmodule

Off_Chip_Protocols/UART_Protocol/UART_Parameterized_BaudRate/6_PISO.v
//Right  shift
module PISO (input [7:0] Data_in,input load, clk,rst,tx_en,output reg Q );
  reg [7:0]Q_temp;
  always @(posedge clk or posedge rst)begin
    if(rst)begin
      Q_temp<={8{1'B0}};
      Q<=0;
    end                // here LSB is  Q[0] and MSB is Q[3]
    else if (load)
     Q_temp<=Data_in;
    else if(tx_en) begin
      Q<=Q_temp[0];
      Q_temp<={1'B0,Q_temp[7:1]};
 
    end

  end
endmodule

Off_Chip_Protocols/UART_Protocol/UART_Parameterized_BaudRate/2_UART_Transmitter.v
`include "7_Parity_Gen.v"
`include "6_PISO.v"

module UART_Transmitter (clk,rst,tx_en,w_en,TDR,Tx,busy);
input clk,rst,tx_en,w_en;
input [7:0] TDR;
output reg Tx;
output reg busy;

//Controller

localparam IDLE=3'B000,
        	START=3'B001,
	        DATA=3'B010,
	        PARITY=3'B011,
	        STOP=3'B100;


reg [2:0] state,next_state;
reg [2:0] counter;
wire load;
wire TSR;
wire parity;

//shift register for converting the parallel input into serial stream of data
//to be sent
 PISO piso(.Data_in(TDR),
	 .load(load),
	 .clk(clk),
	 .rst(rst),
	 .Q(TSR),
	 .tx_en(tx_en));
 

 //Parity generator
 parity_gen  par(.clk(clk),
	 .rst(rst),
	 .x(TDR),
	 .load(load),
	 .odd(parity));
 //sequential logic
always @(posedge clk or posedge rst)begin
	if(rst)
           state<=IDLE;
           
	else
		state<=next_state;

end
//combinational logic
always @(*)begin
	next_state=state;
	case(state)
		IDLE: next_state<=(w_en)? START:IDLE;
		START: next_state<=(tx_en)? DATA:START;
		DATA: next_state<=((tx_en==1)&&(counter==3'd7))? PARITY:DATA;
		PARITY: next_state<=(tx_en)? STOP:PARITY;
		STOP:next_state<=(tx_en)? IDLE:STOP;
	endcase

end
//output logic upon states

assign load =(( state==IDLE)&&( next_state==START));
always @(posedge clk or posedge rst)begin
    if (rst)begin
            Tx<=1;
	    busy<=0;
	    counter<=0;
    end
    else begin
	case(state)
		IDLE:begin
			Tx<=1;
			busy<=0;
			counter<=0;
		end
		START:begin
			Tx<=0;
			busy<=1;
			counter<=0;
		end
		DATA:begin
			Tx<=TSR;
			busy<=1;
                        if(tx_en)
				counter<=counter+1;
		end
		PARITY:begin
			Tx<=parity;
			busy<=1;
			counter<=0;
		end
		STOP:begin
			Tx<=1;
			busy<=1;
			counter<=0;
		end
	endcase
    end
    end
    endmodule

Off_Chip_Protocols/UART_Protocol/UART_Parameterized_BaudRate/5_Receiver_Baud_Gen.v

module receiver_baud_gen #(parameter baudrate=115200,r_frq=100000000)(clk,rst,rx_en);
input clk,rst;
output reg rx_en;

  reg [$clog2(r_frq/baudrate):0] count;

always @(posedge clk or posedge rst)begin

        if(rst)begin
                rx_en<=0;
                count<=0;
        end

  else if(count==(r_frq/baudrate)/16)begin  //count 
                rx_en<=1;
                count<=0;
        end
        else begin
                count<=count+1;
                rx_en<=0;
        end

        end
endmodule

Off_Chip_Protocols/UART_Protocol/UART_Parameterized_BaudRate/4_Transmitter_Baud_Gen.v

module transmitter_baud_gen #(parameter baudrate=115200,t_frq=50000000)(clk,rst,tx_en);
input clk,rst;
output reg tx_en;

reg [$clog2(t_frq/baudrate):0]count;

always @(posedge clk or posedge rst)begin

	if(rst)begin
		tx_en<=0;
		count<=0;
	end

  else if(count==t_frq/baudrate)begin  //count
		tx_en<=1;
	        count<=0;
	end
	else begin
		count<=count+1;
	        tx_en<=0;
	end

        end 
endmodule

Off_Chip_Protocols/UART_Protocol/UART_Parameterized_BaudRate/1_Top.v
`include "2_UART_Transmitter.v"
`include "3_UART_Receiver.v"
`include "4_Transmitter_Baud_Gen.v"
`include "5_Receiver_Baud_Gen.v"

module top #(parameter baudrate=115200,t_frq=50000000,r_frq=100000000) (
input t_clk,r_clk,rst,w_en,
input [7:0] TDR,
output busy,done,frame_err,parity_err,
output [7:0] dout);


wire tx_en,rx_en; //from baud generators to transmitter and receiver
wire Tx;    //serial output from Transmitter to the Receiver
  
reg rx_sync1,rx_sync2;

always @(posedge r_clk or posedge rst) begin
  if(rst)begin
    rx_sync1<=1'b1;
    rx_sync2<=1'b1;
  end else begin
    rx_sync1<=Tx;
    rx_sync2<=rx_sync1;
  end
end
  
  transmitter_baud_gen #(.baudrate(baudrate),.t_frq(t_frq))
                     tbg(.clk(t_clk),
                         .rst(rst),
                         .tx_en(tx_en));
                         
  receiver_baud_gen #(.baudrate(baudrate),.r_frq(r_frq))
                  rbg(.clk(r_clk),
                      .rst(rst),
                      .rx_en(rx_en));
                      
UART_Transmitter  transmit(.clk(t_clk),
                 .rst(rst),
                 .tx_en(tx_en),
                 .w_en(w_en),
                 .TDR(TDR),
                 .Tx(Tx),
                 .busy(busy));
                 
UART_Receiver receive(.clk(r_clk),
              .rst(rst),
              .rx_en(rx_en),
              .Rx(rx_sync2),
              .done(done),
              .dout(dout),
              .frame_err(frame_err),
              .parity_err(parity_err));
              
              
endmodule

Off_Chip_Protocols/UART_Protocol/UART_Parameterized_BaudRate/9_TestBench.v

module uart_tb #(parameter baudrate=115200,t_frq=50000000,r_frq=100000000);

reg t_clk;
reg r_clk;
reg rst;
reg w_en;
reg [7:0]TDR;

wire busy;
wire done;
wire frame_err;
wire parity_err;
wire [7:0] dout;


  top #(.baudrate(baudrate),.t_frq(t_frq),.r_frq(r_frq)) DUT (.t_clk(t_clk),
    .r_clk(r_clk),
    .rst(rst),
    .w_en(w_en),
    .TDR(TDR),
    .busy(busy),
    .done(done),
    .frame_err(frame_err),
    .parity_err(parity_err),
    .dout(dout)
);


always #20 t_clk=~t_clk;   // 50MHz


always #10 r_clk=~r_clk;   //100MHZ

initial begin
    t_clk=0;
    r_clk= 0;
    rst=1;
    w_en=0;
    TDR=8'd0;

    #200;
    rst=0;

   TDR=8'd20;
  repeat(10) begin@(posedge t_clk);

   
     TDR=TDR+20;
    w_en=1;
    @(posedge t_clk);
    w_en=0;
 

    // wait for Receiver to be done
    wait(done==1);

  $display("************************************");
    $display("Sent= %d",TDR);
    $display("Received=%d",dout);
    $display("FrameErr=%b",frame_err);
    $display("ParityErr=%b",parity_err);
  $display("************************************");
end
    #2000;
    $finish;
end

initial begin
    $dumpfile("uart.vcd");
    $dumpvars(0, uart_tb);

$monitor("t=%0t  busy=%b done=%b frame_err=%b parity_err=%b dout=%d",$time,busy,done,frame_err,parity_err,dout);
end

endmodule

Off_Chip_Protocols/UART_Protocol/UART_Parameterized_BaudRate/uart.vcd
$date
	Wed Mar  4 10:23:08 2026
$end
$version
	Icarus Verilog
$end
$timescale
	1s
$end
$scope module uart_tb $end
$var wire 1 ! parity_err $end
$var wire 1 " frame_err $end
$var wire 8 # dout [7:0] $end
$var wire 1 $ done $end
$var wire 1 % busy $end
$var parameter 32 & baudrate $end
$var parameter 32 ' r_frq $end
$var parameter 32 ( t_frq $end
$var reg 8 ) TDR [7:0] $end
$var reg 1 * r_clk $end
$var reg 1 + rst $end
$var reg 1 , t_clk $end
$var reg 1 - w_en $end
$scope module DUT $end
$var wire 8 . TDR [7:0] $end
$var wire 1 * r_clk $end
$var wire 1 + rst $end
$var wire 1 , t_clk $end
$var wire 1 - w_en $end
$var wire 1 / tx_en $end
$var wire 1 0 rx_en $end
$var wire 1 ! parity_err $end
$var wire 1 " frame_err $end
$var wire 8 1 dout [7:0] $end
$var wire 1 $ done $end
$var wire 1 % busy $end
$var wire 1 2 Tx $end
$var parameter 32 3 baudrate $end
$var parameter 32 4 r_frq $end
$var parameter 32 5 t_frq $end
$var reg 1 6 rx_sync1 $end
$var reg 1 7 rx_sync2 $end
$scope module rbg $end
$var wire 1 * clk $end
$var wire 1 + rst $end
$var parameter 32 8 baudrate $end
$var parameter 32 9 r_frq $end
$var reg 11 : count [10:0] $end
$var reg 1 0 rx_en $end
$upscope $end
$scope module receive $end
$var wire 1 7 Rx $end
$var wire 1 * clk $end
$var wire 1 + rst $end
$var wire 1 0 rx_en $end
$var wire 1 ; sample_end $end
$var wire 1 < sample_mid $end
$var wire 1 = sh_en $end
$var wire 1 > o_parity_check $end
$var parameter 3 ? DATA $end
$var parameter 3 @ IDLE $end
$var parameter 3 A PARITY $end
$var parameter 3 B START $end
$var parameter 3 C STOP $end
$var reg 8 D TDR [7:0] $end
$var reg 1 $ done $end
$var reg 8 E dout [7:0] $end
$var reg 1 " frame_err $end
$var reg 3 F index [2:0] $end
$var reg 3 G next_state [2:0] $end
$var reg 1 H o_parity $end
$var reg 1 ! parity_err $end
$var reg 4 I sample [3:0] $end
$var reg 3 J state [2:0] $end
$scope module pc $end
$var wire 8 K Data [7:0] $end
$var wire 1 H Odd_parity $end
$var wire 1 > OpCheck $end
$upscope $end
$upscope $end
$scope module tbg $end
$var wire 1 , clk $end
$var wire 1 + rst $end
$var parameter 32 L baudrate $end
$var parameter 32 M t_frq $end
$var reg 10 N count [9:0] $end
$var reg 1 / tx_en $end
$upscope $end
$scope module transmit $end
$var wire 8 O TDR [7:0] $end
$var wire 1 , clk $end
$var wire 1 P load $end
$var wire 1 + rst $end
$var wire 1 / tx_en $end
$var wire 1 - w_en $end
$var wire 1 Q parity $end
$var wire 1 R TSR $end
$var parameter 3 S DATA $end
$var parameter 3 T IDLE $end
$var parameter 3 U PARITY $end
$var parameter 3 V START $end
$var parameter 3 W STOP $end
$var reg 1 2 Tx $end
$var reg 1 % busy $end
$var reg 3 X counter [2:0] $end
$var reg 3 Y next_state [2:0] $end
$var reg 3 Z state [2:0] $end
$scope module par $end
$var wire 1 , clk $end
$var wire 1 P load $end
$var wire 1 + rst $end
$var wire 8 [ x [7:0] $end
$var reg 1 Q odd $end
$upscope $end
$scope module piso $end
$var wire 8 \ Data_in [7:0] $end
$var wire 1 , clk $end
$var wire 1 P load $end
$var wire 1 + rst $end
$var wire 1 / tx_en $end
$var reg 1 R Q $end
$var reg 8 ] Q_temp [7:0] $end
$upscope $end
$upscope $end
$upscope $end
$upscope $end
$enddefinitions $end
$comment Show the parameter values. $end
$dumpall
b100 W
b1 V
b11 U
b0 T
b10 S
b10111110101111000010000000 M
b11100001000000000 L
b100 C
b1 B
b11 A
b0 @
b10 ?
b101111101011110000100000000 9
b11100001000000000 8
b10111110101111000010000000 5
b101111101011110000100000000 4
b11100001000000000 3
b10111110101111000010000000 (
b101111101011110000100000000 '
b11100001000000000 &
$end
#0
$dumpvars
b0 ]
b0 \
b0 [
b0 Z
b0 Y
b0 X
0R
0Q
0P
b0 O
b0 N
bx K
b0 J
b0 I
0H
b0 G
b0 F
b0 E
bx D
x>
0=
0<
0;
b0 :
17
16
12
b0 1
00
0/
b0 .
0-
0,
1+
0*
b0 )
0%
0$
b0 #
0"
0!
$end
#10
1>
b0 D
b0 K
1*
#20
0*
1,
#30
1*
#40
0*
0,
#50
1*
#60
0*
1,
#70
1*
#80
0*
0,
#90
1*
#100
0*
1,
#110
1*
#120
0*
0,
#130
1*
#140
0*
1,
#150
1*
#160
0*
0,
#170
1*
#180
0*
1,
#190
1*
#200
0*
0,
b10100 )
b10100 .
b10100 O
b10100 [
b10100 \
0+
#210
b1 :
1*
#220
1P
b1 Y
b1 N
1-
b101000 )
b101000 .
b101000 O
b101000 [
b101000 \
0*
1,
#230
b10 :
1*
#240
0*
0,
#250
b11 :
1*
#260
b1 Z
1Q
b101000 ]
b10 N
0P
b1 Y
0-
0*
1,
#270
b100 :
1*
#280
0*
0,
#290
b101 :
1*
#300
b11 N
1%
02
0*
1,
#310
b110 :
06
1*
#320
0*
0,
#330
b1 G
07
b111 :
1*
#340
b100 N
0*
1,
#350
b1000 :
b1 J
1*
#360
0*
0,
#370
b1001 :
1*
#380
b101 N
0*
1,
#390
b1010 :
1*
#400
0*
0,
#410
b1011 :
1*
#420
b110 N
0*
1,
#430
b1100 :
1*
#440
0*
0,
#450
b1101 :
1*
#460
b111 N
0*
1,
#470
b1110 :
1*
#480
0*
0,
#490
b1111 :
1*
#500
b1000 N
0*
1,
#510
b10000 :
1*
#520
0*
0,
#530
b10001 :
1*
#540
b1001 N
0*
1,
#550
b10010 :
1*
#560
0*
0,
#570
b10011 :
1*
#580
b1010 N
0*
1,
#590
b10100 :
1*
#600
0*
0,
#610
b10101 :
1*
#620
b1011 N
0*
1,
#630
b10110 :
1*
#640
0*
0,
#650
b10111 :
1*
#660
b1100 N
0*
1,
#670
b11000 :
1*
#680
0*
0,
#690
b11001 :
1*
#700
b1101 N
0*
1,
#710
b11010 :
1*
#720
0*
0,
#730
b11011 :
1*
#740
b1110 N
0*
1,
#750
b11100 :
1*
#760
0*
0,
#770
b11101 :
1*
#780
b1111 N
0*
1,
#790
b11110 :
1*
#800
0*
0,
#810
b11111 :
1*
#820
b10000 N
0*
1,
#830
b100000 :
1*
#840
0*
0,
#850
b100001 :
1*
#860
b10001 N
0*
1,
#870
b100010 :
1*
#880
0*
0,
#890
b100011 :
1*
#900
b10010 N
0*
1,
#910
b100100 :
1*
#920
0*
0,
#930
b100101 :
1*
#940
b10011 N
0*
1,
#950
b100110 :
1*
#960
0*
0,
#970
b100111 :
1*
#980
b10100 N
0*
1,
#990
b101000 :
1*
#1000
0*
0,
#1010
b101001 :
1*
#1020
b10101 N
0*
1,
#1030
b101010 :
1*
#1040
0*
0,
#1050
b101011 :
1*
#1060
b10110 N
0*
1,
#1070
b101100 :
1*
#1080
0*
0,
#1090
b101101 :
1*
#1100
b10111 N
0*
1,
#1110
b101110 :
1*
#1120
0*
0,
#1130
b101111 :
1*
#1140
b11000 N
0*
1,
#1150
b110000 :
1*
#1160
0*
0,
#1170
b110001 :
1*
#1180
b11001 N
0*
1,
#1190
b110010 :
1*
#1200
0*
0,
#1210
b110011 :
1*
#1220
b11010 N
0*
1,
#1230
b110100 :
1*
#1240
0*
0,
#1250
b110101 :
1*
#1260
b11011 N
0*
1,
#1270
b110110 :
1*
#1280
0*
0,
#1290
b0 :
10
1*
#1300
b11100 N
0*
1,
#1310
00
b1 :
b1 I
1*
#1320
0*
0,
#1330
b10 :
1*
#1340
b11101 N
0*
1,
#1350
b11 :
1*
#1360
0*
0,
#1370
b100 :
1*
#1380
b11110 N
0*
1,
#1390
b101 :
1*
#1400
0*
0,
#1410
b110 :
1*
#1420
b11111 N
0*
1,
#1430
b111 :
1*
#1440
0*
0,
#1450
b1000 :
1*
#1460
b100000 N
0*
1,
#1470
b1001 :
1*
#1480
0*
0,
#1490
b1010 :
1*
#1500
b100001 N
0*
1,
#1510
b1011 :
1*
#1520
0*
0,
#1530
b1100 :
1*
#1540
b100010 N
0*
1,
#1550
b1101 :
1*
#1560
0*
0,
#1570
b1110 :
1*
#1580
b100011 N
0*
1,
#1590
b1111 :
1*
#1600
0*
0,
#1610
b10000 :
1*
#1620
b100100 N
0*
1,
#1630
b10001 :
1*
#1640
0*
0,
#1650
b10010 :
1*
#1660
b100101 N
0*
1,
#1670
b10011 :
1*
#1680
0*
0,
#1690
b10100 :
1*
#1700
b100110 N
0*
1,
#1710
b10101 :
1*
#1720
0*
0,
#1730
b10110 :
1*
#1740
b100111 N
0*
1,
#1750
b10111 :
1*
#1760
0*
0,
#1770
b11000 :
1*
#1780
b101000 N
0*
1,
#1790
b11001 :
1*
#1800
0*
0,
#1810
b11010 :
1*
#1820
b101001 N
0*
1,
#1830
b11011 :
1*
#1840
0*
0,
#1850
b11100 :
1*
#1860
b101010 N
0*
1,
#1870
b11101 :
1*
#1880
0*
0,
#1890
b11110 :
1*
#1900
b101011 N
0*
1,
#1910
b11111 :
1*
#1920
0*
0,
#1930
b100000 :
1*
#1940
b101100 N
0*
1,
#1950
b100001 :
1*
#1960
0*
0,
#1970
b100010 :
1*
#1980
b101101 N
0*
1,
#1990
b100011 :
1*
#2000
0*
0,
#2010
b100100 :
1*
#2020
b101110 N
0*
1,
#2030
b100101 :
1*
#2040
0*
0,
#2050
b100110 :
1*
#2060
b101111 N
0*
1,
#2070
b100111 :
1*
#2080
0*
0,
#2090
b101000 :
1*
#2100
b110000 N
0*
1,
#2110
b101001 :
1*
#2120
0*
0,
#2130
b101010 :
1*
#2140
b110001 N
0*
1,
#2150
b101011 :
1*
#2160
0*
0,
#2170
b101100 :
1*
#2180
b110010 N
0*
1,
#2190
b101101 :
1*
#2200
0*
0,
#2210
b101110 :
1*
#2220
b110011 N
0*
1,
#2230
b101111 :
1*
#2240
0*
0,
#2250
b110000 :
1*
#2260
b110100 N
0*
1,
#2270
b110001 :
1*
#2280
0*
0,
#2290
b110010 :
1*
#2300
b110101 N
0*
1,
#2310
b110011 :
1*
#2320
0*
0,
#2330
b110100 :
1*
#2340
b110110 N
0*
1,
#2350
b110101 :
1*
#2360
0*
0,
#2370
b110110 :
1*
#2380
b110111 N
0*
1,
#2390
b0 :
10
1*
#2400
0*
0,
#2410
b10 I
00
b1 :
1*
#2420
b111000 N
0*
1,
#2430
b10 :
1*
#2440
0*
0,
#2450
b11 :
1*
#2460
b111001 N
0*
1,
#2470
b100 :
1*
#2480
0*
0,
#2490
b101 :
1*
#2500
b111010 N
0*
1,
#2510
b110 :
1*
#2520
0*
0,
#2530
b111 :
1*
#2540
b111011 N
0*
1,
#2550
b1000 :
1*
#2560
0*
0,
#2570
b1001 :
1*
#2580
b111100 N
0*
1,
#2590
b1010 :
1*
#2600
0*
0,
#2610
b1011 :
1*
#2620
b111101 N
0*
1,
#2630
b1100 :
1*
#2640
0*
0,
#2650
b1101 :
1*
#2660
b111110 N
0*
1,
#2670
b1110 :
1*
#2680
0*
0,
#2690
b1111 :
1*
#2700
b111111 N
0*
1,
#2710
b10000 :
1*
#2720
0*
0,
#2730
b10001 :
1*
#2740
b1000000 N
0*
1,
#2750
b10010 :
1*
#2760
0*
0,
#2770
b10011 :
1*
#2780
b1000001 N
0*
1,
#2790
b10100 :
1*
#2800
0*
0,
#2810
b10101 :
1*
#2820
b1000010 N
0*
1,
#2830
b10110 :
1*
#2840
0*
0,
#2850
b10111 :
1*
#2860
b1000011 N
0*
1,
#2870
b11000 :
1*
#2880
0*
0,
#2890
b11001 :
1*
#2900
b1000100 N
0*
1,
#2910
b11010 :
1*
#2920
0*
0,
#2930
b11011 :
1*
#2940
b1000101 N
0*
1,
#2950
b11100 :
1*
#2960
0*
0,
#2970
b11101 :
1*
#2980
b1000110 N
0*
1,
#2990
b11110 :
1*
#3000
0*
0,
#3010
b11111 :
1*
#3020
b1000111 N
0*
1,
#3030
b100000 :
1*
#3040
0*
0,
#3050
b100001 :
1*
#3060
b1001000 N
0*
1,
#3070
b100010 :
1*
#3080
0*
0,
#3090
b100011 :
1*
#3100
b1001001 N
0*
1,
#3110
b100100 :
1*
#3120
0*
0,
#3130
b100101 :
1*
#3140
b1001010 N
0*
1,
#3150
b100110 :
1*
#3160
0*
0,
#3170
b100111 :
1*
#3180
b1001011 N
0*
1,
#3190
b101000 :
1*
#3200
0*
0,
#3210
b101001 :
1*
#3220
b1001100 N
0*
1,
#3230
b101010 :
1*
#3240
0*
0,
#3250
b101011 :
1*
#3260
b1001101 N
0*
1,
#3270
b101100 :
1*
#3280
0*
0,
#3290
b101101 :
1*
#3300
b1001110 N
0*
1,
#3310
b101110 :
1*
#3320
0*
0,
#3330
b101111 :
1*
#3340
b1001111 N
0*
1,
#3350
b110000 :
1*
#3360
0*
0,
#3370
b110001 :
1*
#3380
b1010000 N
0*
1,
#3390
b110010 :
1*
#3400
0*
0,
#3410
b110011 :
1*
#3420
b1010001 N
0*
1,
#3430
b110100 :
1*
#3440
0*
0,
#3450
b110101 :
1*
#3460
b1010010 N
0*
1,
#3470
b110110 :
1*
#3480
0*
0,
#3490
b0 :
10
1*
#3500
b1010011 N
0*
1,
#3510
00
b1 :
b11 I
1*
#3520
0*
0,
#3530
b10 :
1*
#3540
b1010100 N
0*
1,
#3550
b11 :
1*
#3560
0*
0,
#3570
b100 :
1*
#3580
b1010101 N
0*
1,
#3590
b101 :
1*
#3600
0*
0,
#3610
b110 :
1*
#3620
b1010110 N
0*
1,
#3630
b111 :
1*
#3640
0*
0,
#3650
b1000 :
1*
#3660
b1010111 N
0*
1,
#3670
b1001 :
1*
#3680
0*
0,
#3690
b1010 :
1*
#3700
b1011000 N
0*
1,
#3710
b1011 :
1*
#3720
0*
0,
#3730
b1100 :
1*
#3740
b1011001 N
0*
1,
#3750
b1101 :
1*
#3760
0*
0,
#3770
b1110 :
1*
#3780
b1011010 N
0*
1,
#3790
b1111 :
1*
#3800
0*
0,
#3810
b10000 :
1*
#3820
b1011011 N
0*
1,
#3830
b10001 :
1*
#3840
0*
0,
#3850
b10010 :
1*
#3860
b1011100 N
0*
1,
#3870
b10011 :
1*
#3880
0*
0,
#3890
b10100 :
1*
#3900
b1011101 N
0*
1,
#3910
b10101 :
1*
#3920
0*
0,
#3930
b10110 :
1*
#3940
b1011110 N
0*
1,
#3950
b10111 :
1*
#3960
0*
0,
#3970
b11000 :
1*
#3980
b1011111 N
0*
1,
#3990
b11001 :
1*
#4000
0*
0,
#4010
b11010 :
1*
#4020
b1100000 N
0*
1,
#4030
b11011 :
1*
#4040
0*
0,
#4050
b11100 :
1*
#4060
b1100001 N
0*
1,
#4070
b11101 :
1*
#4080
0*
0,
#4090
b11110 :
1*
#4100
b1100010 N
0*
1,
#4110
b11111 :
1*
#4120
0*
0,
#4130
b100000 :
1*
#4140
b1100011 N
0*
1,
#4150
b100001 :
1*
#4160
0*
0,
#4170
b100010 :
1*
#4180
b1100100 N
0*
1,
#4190
b100011 :
1*
#4200
0*
0,
#4210
b100100 :
1*
#4220
b1100101 N
0*
1,
#4230
b100101 :
1*
#4240
0*
0,
#4250
b100110 :
1*
#4260
b1100110 N
0*
1,
#4270
b100111 :
1*
#4280
0*
0,
#4290
b101000 :
1*
#4300
b1100111 N
0*
1,
#4310
b101001 :
1*
#4320
0*
0,
#4330
b101010 :
1*
#4340
b1101000 N
0*
1,
#4350
b101011 :
1*
#4360
0*
0,
#4370
b101100 :
1*
#4380
b1101001 N
0*
1,
#4390
b101101 :
1*
#4400
0*
0,
#4410
b101110 :
1*
#4420
b1101010 N
0*
1,
#4430
b101111 :
1*
#4440
0*
0,
#4450
b110000 :
1*
#4460
b1101011 N
0*
1,
#4470
b110001 :
1*
#4480
0*
0,
#4490
b110010 :
1*
#4500
b1101100 N
0*
1,
#4510
b110011 :
1*
#4520
0*
0,
#4530
b110100 :
1*
#4540
b1101101 N
0*
1,
#4550
b110101 :
1*
#4560
0*
0,
#4570
b110110 :
1*
#4580
b1101110 N
0*
1,
#4590
b0 :
10
1*
#4600
0*
0,
#4610
b100 I
00
b1 :
1*
#4620
b1101111 N
0*
1,
#4630
b10 :
1*
#4640
0*
0,
#4650
b11 :
1*
#4660
b1110000 N
0*
1,
#4670
b100 :
1*
#4680
0*
0,
#4690
b101 :
1*
#4700
b1110001 N
0*
1,
#4710
b110 :
1*
#4720
0*
0,
#4730
b111 :
1*
#4740
b1110010 N
0*
1,
#4750
b1000 :
1*
#4760
0*
0,
#4770
b1001 :
1*
#4780
b1110011 N
0*
1,
#4790
b1010 :
1*
#4800
0*
0,
#4810
b1011 :
1*
#4820
b1110100 N
0*
1,
#4830
b1100 :
1*
#4840
0*
0,
#4850
b1101 :
1*
#4860
b1110101 N
0*
1,
#4870
b1110 :
1*
#4880
0*
0,
#4890
b1111 :
1*
#4900
b1110110 N
0*
1,
#4910
b10000 :
1*
#4920
0*
0,
#4930
b10001 :
1*
#4940
b1110111 N
0*
1,
#4950
b10010 :
1*
#4960
0*
0,
#4970
b10011 :
1*
#4980
b1111000 N
0*
1,
#4990
b10100 :
1*
#5000
0*
0,
#5010
b10101 :
1*
#5020
b1111001 N
0*
1,
#5030
b10110 :
1*
#5040
0*
0,
#5050
b10111 :
1*
#5060
b1111010 N
0*
1,
#5070
b11000 :
1*
#5080
0*
0,
#5090
b11001 :
1*
#5100
b1111011 N
0*
1,
#5110
b11010 :
1*
#5120
0*
0,
#5130
b11011 :
1*
#5140
b1111100 N
0*
1,
#5150
b11100 :
1*
#5160
0*
0,
#5170
b11101 :
1*
#5180
b1111101 N
0*
1,
#5190
b11110 :
1*
#5200
0*
0,
#5210
b11111 :
1*
#5220
b1111110 N
0*
1,
#5230
b100000 :
1*
#5240
0*
0,
#5250
b100001 :
1*
#5260
b1111111 N
0*
1,
#5270
b100010 :
1*
#5280
0*
0,
#5290
b100011 :
1*
#5300
b10000000 N
0*
1,
#5310
b100100 :
1*
#5320
0*
0,
#5330
b100101 :
1*
#5340
b10000001 N
0*
1,
#5350
b100110 :
1*
#5360
0*
0,
#5370
b100111 :
1*
#5380
b10000010 N
0*
1,
#5390
b101000 :
1*
#5400
0*
0,
#5410
b101001 :
1*
#5420
b10000011 N
0*
1,
#5430
b101010 :
1*
#5440
0*
0,
#5450
b101011 :
1*
#5460
b10000100 N
0*
1,
#5470
b101100 :
1*
#5480
0*
0,
#5490
b101101 :
1*
#5500
b10000101 N
0*
1,
#5510
b101110 :
1*
#5520
0*
0,
#5530
b101111 :
1*
#5540
b10000110 N
0*
1,
#5550
b110000 :
1*
#5560
0*
0,
#5570
b110001 :
1*
#5580
b10000111 N
0*
1,
#5590
b110010 :
1*
#5600
0*
0,
#5610
b110011 :
1*
#5620
b10001000 N
0*
1,
#5630
b110100 :
1*
#5640
0*
0,
#5650
b110101 :
1*
#5660
b10001001 N
0*
1,
#5670
b110110 :
1*
#5680
0*
0,
#5690
b0 :
10
1*
#5700
b10001010 N
0*
1,
#5710
00
b1 :
b101 I
1*
#5720
0*
0,
#5730
b10 :
1*
#5740
b10001011 N
0*
1,
#5750
b11 :
1*
#5760
0*
0,
#5770
b100 :
1*
#5780
b10001100 N
0*
1,
#5790
b101 :
1*
#5800
0*
0,
#5810
b110 :
1*
#5820
b10001101 N
0*
1,
#5830
b111 :
1*
#5840
0*
0,
#5850
b1000 :
1*
#5860
b10001110 N
0*
1,
#5870
b1001 :
1*
#5880
0*
0,
#5890
b1010 :
1*
#5900
b10001111 N
0*
1,
#5910
b1011 :
1*
#5920
0*
0,
#5930
b1100 :
1*
#5940
b10010000 N
0*
1,
#5950
b1101 :
1*
#5960
0*
0,
#5970
b1110 :
1*
#5980
b10010001 N
0*
1,
#5990
b1111 :
1*
#6000
0*
0,
#6010
b10000 :
1*
#6020
b10010010 N
0*
1,
#6030
b10001 :
1*
#6040
0*
0,
#6050
b10010 :
1*
#6060
b10010011 N
0*
1,
#6070
b10011 :
1*
#6080
0*
0,
#6090
b10100 :
1*
#6100
b10010100 N
0*
1,
#6110
b10101 :
1*
